Workbook

Sheet Cover Page
B2: BHARAT HEAVY ELECTRICALS LIMITED (BHEL)
B3: Integrated Financial Model & Equity Valuation | NSE: BHEL | BSE: 500103
B6: Company | C6: Bharat Heavy Electricals Ltd (Maharatna CPSE, Govt. of India)
B7: Sector | C7: Capital Goods / Heavy Electrical Equipment
B8: Reporting basis | C8: Consolidated, Indian Accounting Standards (Ind-AS)
B9: Currency / Units | C9: INR Crore (per-share in INR)
B10: Historical period | C10: FY2020 - FY2026 (reported)
B11: Forecast period | C11: FY2027 - FY2033 (7 years, analyst projections)
B12: Valuation date | C12: 27-Jun-2026
B13: Last traded price | C13: INR 403 (25-Jun-2026)
B14: Shares outstanding | C14: ~348.0 crore (Face value INR 2)
B15: Promoter (Govt. of India) | C15: 58.17%
B17: Income statement format
B18: Sales - COGS = Gross Profit; less Operating Expenses (Employee, Selling & admin) = EBITDA;
B19: less D&A = EBIT; +Other Income -Interest = PBT; less Tax +/- Adjustments = PAT.
B21: Formatting legend
B22: Black | C22: Hardcoded input / reported data
B23: Blue | C23: In-sheet formula
B24: Green | C24: Link to another worksheet
B25: Gold fill | C25: Editable assumption / input
B27: Data sources & caveats
B28: Headline financials FY20-26: BHEL BSE/NSE filings (consolidated), aggregated via Screener.in.
B29: Order book, inflow & segment data: BHEL results releases & Directors' Report (standalone basis).
B30: Detailed expense split (COGS / employee / selling & admin) and detailed balance-sheet sub-lines
B31: are analyst estimates clearly flagged and anchored to the reported audited TOTALS.
B32: Peer multiples on Relative Valuation are indicative; refresh with live data before use.

Sheet Assumptions
A1: ASSUMPTIONS
B2: Scenario Switch | D2: Base | F2: <- toggles the VARIABLE drivers below; revenue, margins, cash flow & valuation recalculate
A3: A. VARIABLE ASSUMPTIONS (Base / Best / Bear - selected by Scenario Switch) | I3: Sales growth is DERIVED (Revenue Build-up): Revenue = Execution rate x Opening order book; Closing OB = Opening + Inflow - Revenue.
A4: ratios / INR Crore | B4: FY2020 | C4: FY2021 | D4: FY2022 | E4: FY2023 | F4: FY2024 | G4: FY2025 | H4: FY2026 | I4: FY2027 | J4: FY2028 | K4: FY2029 | L4: FY2030 | M4: FY2031 | N4: FY2032 | O4: FY2033
A5: New order inflow (INR Cr) [revenue driver] | I5: =IF($D$2="Best",I7,IF($D$2="Bear",I8,I6)) | J5: =IF($D$2="Best",J7,IF($D$2="Bear",J8,J6)) | K5: =IF($D$2="Best",K7,IF($D$2="Bear",K8,K6)) | L5: =IF($D$2="Best",L7,IF($D$2="Bear",L8,L6)) | M5: =IF($D$2="Best",M7,IF($D$2="Bear",M8,M6)) | N5: =IF($D$2="Best",N7,IF($D$2="Bear",N8,N6)) | O5: =IF($D$2="Best",O7,IF($D$2="Bear",O8,O6)) | P5: Demand driver: thermal/T&D/defence ordering. Best=accelerated power capex cycle; Bear=delayed ordering.
A6: Base | I6: 78000 | J6: 82000 | K6: 86000 | L6: 90000 | M6: 92000 | N6: 94000 | O6: 96000
A7: Best | I7: 90000 | J7: 95000 | K7: 100000 | L7: 105000 | M7: 108000 | N7: 110000 | O7: 112000
A8: Bear | I8: 62000 | J8: 64000 | K8: 66000 | L8: 68000 | M8: 70000 | N8: 72000 | O8: 74000
A10: Execution rate (revenue / opening order book) [revenue driver] | I10: =IF($D$2="Best",I12,IF($D$2="Bear",I13,I11)) | J10: =IF($D$2="Best",J12,IF($D$2="Bear",J13,J11)) | K10: =IF($D$2="Best",K12,IF($D$2="Bear",K13,K11)) | L10: =IF($D$2="Best",L12,IF($D$2="Bear",L13,L11)) | M10: =IF($D$2="Best",M12,IF($D$2="Bear",M13,M11)) | N10: =IF($D$2="Best",N12,IF($D$2="Bear",N13,N11)) | O10: =IF($D$2="Best",O12,IF($D$2="Bear",O13,O11)) | P10: Order-book-to-revenue conversion; rises with capacity utilisation & supply-chain normalisation.
A11: Base | I11: 0.165 | J11: 0.17 | K11: 0.175 | L11: 0.18 | M11: 0.185 | N11: 0.19 | O11: 0.195
A12: Best | I12: 0.175 | J12: 0.182 | K12: 0.19 | L12: 0.197 | M12: 0.205 | N12: 0.21 | O12: 0.215
A13: Bear | I13: 0.15 | J13: 0.152 | K13: 0.155 | L13: 0.158 | M13: 0.16 | N13: 0.162 | O13: 0.165
A15: EBITDA margin (% revenue) | I15: =IF($D$2="Best",I17,IF($D$2="Bear",I18,I16)) | J15: =IF($D$2="Best",J17,IF($D$2="Bear",J18,J16)) | K15: =IF($D$2="Best",K17,IF($D$2="Bear",K18,K16)) | L15: =IF($D$2="Best",L17,IF($D$2="Bear",L18,L16)) | M15: =IF($D$2="Best",M17,IF($D$2="Bear",M18,M16)) | N15: =IF($D$2="Best",N17,IF($D$2="Bear",N18,N16)) | O15: =IF($D$2="Best",O17,IF($D$2="Bear",O18,O16)) | P15: Operating leverage on a largely fixed cost base; commodity (steel/copper) & pricing risk.
A16: Base | I16: 0.075 | J16: 0.085 | K16: 0.095 | L16: 0.105 | M16: 0.11 | N16: 0.115 | O16: 0.12
A17: Best | I17: 0.09 | J17: 0.1 | K17: 0.11 | L17: 0.12 | M17: 0.125 | N17: 0.13 | O17: 0.135
A18: Bear | I18: 0.06 | J18: 0.065 | K18: 0.072 | L18: 0.08 | M18: 0.085 | N18: 0.09 | O18: 0.095
A20: B. FIXED ASSUMPTIONS (structural / policy - constant across scenarios)
A21: ratios / INR Crore | B21: FY2020 | C21: FY2021 | D21: FY2022 | E21: FY2023 | F21: FY2024 | G21: FY2025 | H21: FY2026 | I21: FY2027 | J21: FY2028 | K21: FY2029 | L21: FY2030 | M21: FY2031 | N21: FY2032 | O21: FY2033
A22: Consolidation uplift (consol vs standalone rev) % | I22: 0.02 | J22: 0.02 | K22: 0.02 | L22: 0.02 | M22: 0.02 | N22: 0.02 | O22: 0.02 | P22: Subsidiary/JV contribution to revenue; historical 0-6% (FY26 ~0%).
A23: Other income (% revenue) | I23: 0.018 | J23: 0.018 | K23: 0.018 | L23: 0.018 | M23: 0.018 | N23: 0.018 | O23: 0.018
A24: Employee cost (% revenue) | I24: 0.135 | J24: 0.128 | K24: 0.122 | L24: 0.116 | M24: 0.112 | N24: 0.108 | O24: 0.105
A25: Subcontracting & erection (% revenue, in COGS) | I25: 0.085 | J25: 0.085 | K25: 0.085 | L25: 0.085 | M25: 0.085 | N25: 0.085 | O25: 0.085
A26: Selling & admin (% revenue) | I26: 0.075 | J26: 0.075 | K26: 0.075 | L26: 0.075 | M26: 0.075 | N26: 0.075 | O26: 0.075
A27: COGS: Steel (% revenue) | I27: 0.12 | J27: 0.12 | K27: 0.12 | L27: 0.12 | M27: 0.12 | N27: 0.12 | O27: 0.12
A28: COGS: Copper (% revenue) | I28: 0.05 | J28: 0.05 | K28: 0.05 | L28: 0.05 | M28: 0.05 | N28: 0.05 | O28: 0.05
A29: COGS: Electrical & electronic components (% rev) | I29: 0.1 | J29: 0.1 | K29: 0.1 | L29: 0.1 | M29: 0.1 | N29: 0.1 | O29: 0.1
A30: COGS: Imported components (% revenue) | I30: 0.08 | J30: 0.08 | K30: 0.08 | L30: 0.08 | M30: 0.08 | N30: 0.08 | O30: 0.08
A31: OpEx: Selling & distribution (% revenue) | I31: 0.025 | J31: 0.025 | K31: 0.025 | L31: 0.025 | M31: 0.025 | N31: 0.025 | O31: 0.025
A32: OpEx: Research & development (% revenue) | I32: 0.025 | J32: 0.025 | K32: 0.025 | L32: 0.025 | M32: 0.025 | N32: 0.025 | O32: 0.025
A33: Revenue mix: Power segment % | I33: 0.75 | J33: 0.75 | K33: 0.75 | L33: 0.75 | M33: 0.75 | N33: 0.75 | O33: 0.75
A34: Revenue mix: Industry segment % | I34: 0.22 | J34: 0.22 | K34: 0.22 | L34: 0.22 | M34: 0.22 | N34: 0.22 | O34: 0.22
... A50: Interest rate on opening debt | I50: 0.085 | J50: 0.085 | K50: 0.085 | L50: 0.085 | M50: 0.085 | N50: 0.085 | O50: 0.085
A51: LT borrowings (% of total debt) | I51: 0.02 | J51: 0.02 | K51: 0.02 | L51: 0.02 | M51: 0.02 | N51: 0.02 | O51: 0.02 | P51: BHEL debt almost entirely short-term (FY26 LT only Rs168 cr ~2%).
A52: Other non-current assets (closing) | I52: 15500 | J52: 16000 | K52: 16500 | L52: 17000 | M52: 17500 | N52: 18000 | O52: 18500
A53: Other non-current liabilities (closing) | I53: 6200 | J53: 6400 | K53: 6600 | L53: 6800 | M53: 7000 | N53: 7200 | O53: 7400
A55: WACC & valuation inputs
A56: Risk-free rate (10Y India G-Sec) | C56: 0.068
A57: Levered beta | C57: 1.25
A58: Equity risk premium | C58: 0.065
A59: Pre-tax cost of debt | C59: 0.085
A60: Marginal tax rate (WACC) | C60: 0.25
A61: Target weight of debt | C61: 0.15
A62: Target weight of equity | C62: 0.85
A63: Terminal growth rate | C63: 0.045
A64: Cost of equity (Ke = Rf + B x ERP) | C64: ='Assumptions'!C56+'Assumptions'!C57*'Assumptions'!C58
A65: WACC (We*Ke + Wd*Kd*(1-t)) | C65: ='Assumptions'!C62*'Assumptions'!C64+'Assumptions'!C61*'Assumptions'!C59*(1-'Assumptions'!C60)
A66: Shares outstanding (crore) | C66: 348.05
A67: Current market price (INR) | C67: 403
A68: Face value (INR) | C68: 2
A70: C. WORKING-CAPITAL DETAIL (current vs non-current; % of revenue unless noted)
A71: driver | I71: 2027 | J71: 2028 | K71: 2029 | L71: 2030 | M71: 2031 | N71: 2032 | O71: 2033 | P71: Rationale
A72: Trade receivables - current (% rev) | I72: 0.2 | J72: 0.2 | K72: 0.2 | L72: 0.2 | M72: 0.2 | N72: 0.2 | O72: 0.2 | P72: FY26 actual 20.1% of revenue (~73 days).
A73: Trade receivables - non-current (% rev) | I73: 0.072 | J73: 0.067 | K73: 0.062 | L73: 0.057 | M73: 0.052 | N73: 0.047 | O73: 0.042 | P73: Long-dated/disputed (incl. Sudan); FY26 7.2%, runs down.
A74: Inventories (% rev) | I74: 0.395 | J74: 0.39 | K74: 0.385 | L74: 0.38 | M74: 0.375 | N74: 0.37 | O74: 0.365 | P74: FY26 39.5% of revenue; eases with execution.
A75: Contract assets - current (% rev) | I75: 0.45 | J75: 0.44 | K75: 0.43 | L75: 0.42 | M75: 0.41 | N75: 0.4 | O75: 0.39 | P75: Unbilled billable <12m; FY26 45.0%.
A76: Contract assets - non-current (% rev) | I76: 0.4 | J76: 0.38 | K76: 0.36 | L76: 0.34 | M76: 0.32 | N76: 0.3 | O76: 0.28 | P76: Long-cycle unbilled; FY26 42.0%, declines.
A77: (Deferred tax assets held flat at FY26) | I77: 3533 | P77: Held flat at FY26 audited level (Rs 3,533 cr).
A78: Other current assets residual (% rev) | I78: 0.126 | J78: 0.124 | K78: 0.122 | L78: 0.12 | M78: 0.118 | N78: 0.116 | O78: 0.114 | P78: Deposits, current tax & advances ex-contract; FY26 12.6%.
A79: Other non-current assets residual growth % | I79: 0.03 | J79: 0.03 | K79: 0.03 | L79: 0.03 | M79: 0.03 | N79: 0.03 | O79: 0.03 | P79: LT deposits & loans; slow growth.
A80: Trade payables - current (% rev) | I80: 0.311 | J80: 0.311 | K80: 0.305 | L80: 0.305 | M80: 0.3 | N80: 0.3 | O80: 0.295 | P80: FY26 31.1% of revenue (~167 days COGS).
A81: (Trade payables non-current held flat) | I81: 1343 | P81: Held flat at FY26 (Rs 1,343 cr).
A82: Contract liabilities - current (% rev) | I82: 0.27 | J82: 0.27 | K82: 0.26 | L82: 0.26 | M82: 0.25 | N82: 0.25 | O82: 0.24 | P82: Customer advances <12m; FY26 27.0%.
A83: Contract liabilities - non-current (% rev) | I83: 0.38 | J83: 0.36 | K83: 0.34 | L83: 0.32 | M83: 0.3 | N83: 0.28 | O83: 0.26 | P83: LT customer advances (interest-free WC); FY26 39.7%.
A84: Provisions - current (% rev) | I84: 0.057 | J84: 0.057 | K84: 0.056 | L84: 0.056 | M84: 0.055 | N84: 0.055 | O84: 0.054 | P84: Warranty/LD/employee; FY26 5.7%.
A85: Long-term provisions growth % | I85: 0.03 | J85: 0.03 | K85: 0.03 | L85: 0.03 | M85: 0.03 | N85: 0.03 | O85: 0.03 | P85: Warranty & employee-benefit provisions.
A86: Other current liabilities residual (% rev) | I86: 0.082 | J86: 0.082 | K86: 0.08 | L86: 0.08 | M86: 0.078 | N86: 0.078 | O86: 0.076 | P86: Statutory/employee dues, deposits ex-contract & provisions; FY26 8.2%.
A87: Other non-current liabilities residual growth % | I87: 0.04 | J87: 0.04 | K87: 0.04 | L87: 0.04 | M87: 0.04 | N87: 0.04 | O87: 0.04 | P87: LT deposits & deferred grants.

Sheet Assumptions Rationale
A1: ASSUMPTIONS RATIONALE - basis for every forecast driver
A2: Each driver documents: why reasonable | historical support | management guidance | macro / industry driver | sensitivity.
A3: Driver | B3: Base case | C3: Rationale (historical support | management guidance | macro/industry driver | sensitivity)
A4: REVENUE & ORDER BOOK
A5: Execution rate | B5: 16.5%->19.5% | C5: Revenue recognised as a % of opening order book. Historically BHEL executed ~15-17% of opening OB p.a.; order book is ~7x revenue. Ramp reflects rising capacity utilisation (~65%->80%) and faster thermal execution as supply chains normalise. Sensitivity: +/-1pp ~ +/-Rs2,400-4,000 cr revenue.
A6: Order inflow | B6: Rs78k->96k cr | C6: FY25 record inflow Rs92,535 cr; FY26 ~Rs75,000 cr. Driven by ~80 GW thermal pipeline (NTPC/NLC/state gencos) to FY32, plus T&D, railways and defence diversification. Set conservatively below the FY25 peak; macro driver = power capex super-cycle.
A7: Revenue mix - Power | B7: 75% | C7: BHEL core; power was ~75-80% of revenue historically (FY26 power Rs25,407 cr). Thermal ordering remains dominant near-term.
A8: Revenue mix - Industry | B8: 22% | C8: Rising diversification (industrial systems, transportation, defence). Industry segment grew strongly in FY25-26; balance ~3% is exports/renewables.
A9: COSTS
A10: EBITDA margin | B10: 7.5%->12.0% | C10: Historical FY24 3.0%, FY25 4.9%, FY26 6.9%. Expansion from operating leverage over a largely fixed employee/overhead base, better project mix and roll-off of legacy low-margin orders. Management targets low-teens; peer capital-goods margins 10-18%. Sensitivity: 1pp ~ Rs400-800 cr EBITDA.
A11: Steel (% rev) | B11: 12% | C11: Boilers, turbines and structurals are steel-intensive. Key commodity exposure; +10% steel price ~ +1.2pp COGS. Reflects BHEL bill-of-materials.
A12: Copper (% rev) | B12: 5% | C12: Generators, transformers and windings are copper-intensive. Exposed to LME copper prices.
A13: Electrical & electronic components | B13: 10% | C13: Control systems, switchgear, instrumentation and electronics content in power equipment.
A14: Imported components | B14: 8% | C14: High-tech sub-assemblies imported; FX and import-duty sensitive. Localisation drive aims to reduce this over time.
A15: Other materials & consumables | B15: residual | C15: Balancing item so that materials + subcontracting + opex reconcile to the target EBITDA margin (avoids double-counting).
A16: Subcontracting & erection | B16: 8.5% | C16: Civil works and site erection largely outsourced; scales with project execution. Historical ~8-9%.
A17: Employee cost (% rev) | B17: 13.5%->10.5% | C17: BHEL employee cost is structurally high (~Rs5,300-6,000 cr, broadly flat in absolute terms). Falls as a % as revenue scales (operating leverage); workforce declining ~33,500->25,500 via attrition.
A18: Selling & distribution | B18: 2.5% | C18: Bid/marketing, logistics, liquidated-damages and warranty-related selling costs; consistent with historical SG&A composition.
A19: Administrative (% rev) | B19: ~2.5% (residual) | C19: Corporate overheads; residual within total selling/admin so opex reconciles.
A20: Research & development | B20: 2.5% | C20: BHEL discloses R&D at ~2.5% of turnover; strategic for supercritical/USC, hydrogen/electrolysers, defence and localisation.
A21: Depreciation rate | B21: 9.5% of opening net block | C21: Consistent with historical D&A / net block (~9-10%); plant & machinery weighted asset base.
A22: Capex | B22: Rs600-950 cr | C22: Modernisation plus new capacity for renewables, defence and electrolysers. Historical capex Rs300-900 cr; internally funded.
A23: WORKING CAPITAL
A24: Receivable days | B24: 75 | C24: Historical 49-121; recent ~73-76. Large PSU/SEB customers but collections improving. Anchored to recent levels.
A25: Inventory days | B25: 210->190 | C25: Historical 212-333; long manufacturing/project cycle. Gradual improvement assumed from better execution and planning.
A26: Payable days | B26: 175 | C26: Historical 167-345; normalised to ~175 supplier credit.
A27: Contract assets (% rev) | B27: 23.5% | C27: Unbilled revenue on long-cycle EPC projects under percentage-of-completion accounting.
A28: Contract liabilities / advances | B28: 35.5% | C28: BHEL receives large customer advances on orders - a key working-capital funding source; scales with order activity.
A29: Other non-current assets | B29: Rs15.5k->18.5k cr | C29: Deferred tax assets (large, from past losses), long-term/legacy trade receivables and retention, long-term loans & deposits. Held roughly flat / slow growth. Breakup ~40% DTA / 35% LT receivables / 25% loans & deposits.
A30: Other non-current liabilities | B30: Rs6.2k->7.4k cr | C30: Lease liabilities, long-term provisions (warranty & employee benefits) and deferred tax liabilities. Breakup ~30% leases / 50% provisions / 20% DTL & other.
A31: Other current/NC growth | B31: 3% p.a. | C31: Structural balance-sheet items grow slowly, not 1:1 with revenue, to avoid overstating working-capital drag.
A32: CWIP / Investments | B32: Rs400 cr / Rs310-370 cr | C32: CWIP steady-state low (capex flows quickly to assets); investments = JV/associate stakes, modest growth.
A33: CAPITAL STRUCTURE & TAX
A34: LT vs ST borrowings | B34: 35% LT / 65% ST | C34: BHEL borrowings are largely short-term working-capital lines; ~35% assumed long-term/leases. Editable split.
A35: New borrowings / repayment | B35: 0 / Rs1,000 cr p.a. | C35: Strong forecast FCF and large cash allow steady deleveraging; gross debt declines over the horizon.
A36: Interest rate | B36: 8.5% | C36: Blended cost on borrowings; consistent with historical finance cost / average debt and the current rate environment.
A37: Tax rate | B37: 25% | C37: BHEL on the new corporate-tax regime (~25.17%); normalised to 25%.
A38: Dividend payout | B38: 30% | C38: CPSE/DIPAM policy (~30% of PAT or 5% of net worth); historical payout 30-33%.
A39: VALUATION (DCF)
A40: Risk-free rate | B40: 6.8% | C40: ~India 10-year G-Sec yield.
A41: Beta | B41: 1.25 | C41: BHEL is a high-beta cyclical capital-goods PSU; levered beta > 1.
A42: Equity risk premium | B42: 6.5% | C42: India ERP ~6-7%.
A43: Cost of debt / weights | B43: 8.5% / 15% D, 85% E | C43: Low leverage; target structure mostly equity. After-tax Kd used in WACC.
A44: Terminal growth | B44: 4.5% | C44: Below long-run nominal GDP (~10-11%); conservative perpetuity for a mature franchise (~inflation + modest real growth).
A45: WACC (derived) | B45: ~13.6% | C45: We*Ke + Wd*Kd*(1-t); high due to elevated equity beta. Tested on the Sensitivity sheet vs terminal growth.

Sheet Historical Financial Statements
A1: HISTORICAL FINANCIAL STATEMENTS
A3: A. INCOME STATEMENT
A4: Particulars | B4: FY2020 | C4: FY2021 | D4: FY2022 | E4: FY2023 | F4: FY2024 | G4: FY2025 | H4: FY2026 | I4: FY2027 | J4: FY2028 | K4: FY2029 | L4: FY2030 | M4: FY2031 | N4: FY2032 | O4: FY2033
A5: Sales | B5: 21463 | C5: 17309 | D5: 21211 | E5: 23365 | F5: 23893 | G5: 28339 | H5: 33782
A6: Total COGS | B6: 14496 | C6: 13657 | D6: 13783 | E6: 15721 | F6: 16682 | G6: 20040 | H6: 24040
A7: Gross Profit | B7: =B5-B6 | C7: =C5-C6 | D7: =D5-D6 | E7: =E5-E6 | F7: =F5-F6 | G7: =G5-G6 | H7: =H5-H6
A8: Operating Expenses
A9: Employee Cost | B9: 6000 | C9: 5800 | D9: 5500 | E9: 5400 | F9: 5300 | G9: 5500 | H9: 5700
A10: Selling and admin | B10: 1100 | C10: 900 | D10: 1100 | E10: 1200 | F10: 1200 | G10: 1400 | H10: 1700
A11: Total Operating Expenses | B11: =B9+B10 | C11: =C9+C10 | D11: =D9+D10 | E11: =E9+E10 | F11: =F9+F10 | G11: =G9+G10 | H11: =H9+H10
A12: EBITDA | B12: =B7-B11 | C12: =C7-C11 | D12: =D7-D11 | E12: =E7-E11 | F12: =F7-F11 | G12: =G7-G11 | H12: =H7-H11
A13: Depreciation & Amortization | B13: 503 | C13: 473 | D13: 314 | E13: 260 | F13: 249 | G13: 272 | H13: 316
A14: EBIT | B14: =B12-B13 | C14: =C12-C13 | D14: =D12-D13 | E14: =E12-E13 | F14: =F12-F13 | G14: =G12-G13 | H14: =H12-H13
A15: Other Income | B15: 590 | C15: 393 | D15: 405 | E15: 544 | F15: 608 | G15: 524 | H15: 869
A16: Interest Paid | B16: 613 | C16: 467 | D16: 448 | E16: 612 | F16: 828 | G16: 906 | H16: 756
A17: Profit Before Tax (PBT) | B17: =B14+B15-B16 | C17: =C14+C15-C16 | D17: =D14+D15-D16 | E17: =E14+E15-E16 | F17: =F14+F15-F16 | G17: =G14+G15-G16 | H17: =H14+H15-H16
A18: Tax | B18: 809 | C18: -896 | D18: 25 | E18: 62 | F18: -39 | G18: 212 | H18: 539
A19: Adjustments | B19: 0 | C19: 0 | D19: 0 | E19: 0 | F19: 0 | G19: 0 | H19: 0
A20: Profit After Tax (PAT) | B20: =B17-B18+B19 | C20: =C17-C18+C19 | D20: =D17-D18+D19 | E20: =E17-E18+E19 | F20: =F17-F18+F19 | G20: =G17-G18+G19 | H20: =H17-H18+H19
A21: EPS (INR) | B21: =B20/'Assumptions'!C66 | C21: =C20/'Assumptions'!C66 | D21: =D20/'Assumptions'!C66 | E21: =E20/'Assumptions'!C66 | F21: =F20/'Assumptions'!C66 | G21: =G20/'Assumptions'!C66 | H21: =H20/'Assumptions'!C66
A22: Dividend | B22: 0 | C22: 0 | D22: 138 | E22: 137 | F22: 87 | G22: 176 | H22: 487
A23: Memo: total operating cost (COGS+OpEx) | B23: =B6+B11 | C23: =C6+C11 | D23: =D6+D11 | E23: =E6+E11 | F23: =F6+F11 | G23: =G6+G11 | H23: =H6+H11
A24: COGS, Employee & Selling/admin split are analyst estimates anchored to reported total opex; Sales, EBITDA, D&A, interest, tax, PAT are reported.
A26: B. BALANCE SHEET
A27: Particulars | B27: FY2020 | C27: FY2021 | D27: FY2022 | E27: FY2023 | F27: FY2024 | G27: FY2025 | H27: FY2026 | I27: FY2027 | J27: FY2028 | K27: FY2029 | L27: FY2030 | M27: FY2031 | N27: FY2032 | O27: FY2033
A28: Net property, plant & equipment | B28: 2817 | C28: 2491 | D28: 2398 | E28: 2476 | F28: 2574 | G28: 2947 | H28: 3094
A29: Capital work-in-progress | B29: 314 | C29: 420 | D29: 431 | E29: 354 | F29: 308 | G29: 195 | H29: 399
A30: Investments | B30: 162 | C30: 185 | D30: 205 | E30: 235 | F30: 256 | G30: 276 | H30: 302
A31: Other assets (inventory, receivables, cash, contract & other) | B31: 56998 | C31: 52864 | D31: 53956 | E31: 54599 | F31: 56646 | G31: 65431 | H31: 72390
A32: TOTAL ASSETS | B32: =SUM(B28:B31) | C32: =SUM(C28:C31) | D32: =SUM(D28:D31) | E32: =SUM(E28:E31) | F32: =SUM(F28:F31) | G32: =SUM(G28:G31) | H32: =SUM(H28:H31)
A33: Equity share capital | B33: 696 | C33: 696 | D33: 696 | E33: 696 | F33: 696 | G33: 696 | H33: 696
A34: Other equity (reserves & surplus) | B34: 27964 | C34: 25287 | D34: 25810 | E34: 23682 | F34: 23742 | G34: 24026 | H34: 25450
A35: Borrowings (incl. lease liabilities) | B35: 5080 | C35: 4951 | D35: 4830 | E35: 5454 | F35: 8856 | G35: 9015 | H35: 8187
A36: Other liabilities (payables, advances, provisions) | B36: 26550 | C36: 25025 | D36: 25654 | E36: 27832 | F36: 26489 | G36: 35112 | H36: 41852
A37: TOTAL EQUITY & LIABILITIES | B37: =SUM(B33:B36) | C37: =SUM(C33:C36) | D37: =SUM(D33:D36) | E37: =SUM(E33:E36) | F37: =SUM(F33:F36) | G37: =SUM(G33:G36) | H37: =SUM(H33:H36)
A38: Balance check (TA - TE&L) | B38: =B32-B37 | C38: =C32-C37 | D38: =D32-D37 | E38: =E32-E37 | F38: =F32-F37 | G38: =G32-G37 | H38: =H32-H37
A40: C. CASH FLOW STATEMENT (reported summary)
A41: Particulars | B41: FY2020 | C41: FY2021 | D41: FY2022 | E41: FY2023 | F41: FY2024 | G41: FY2025 | H41: FY2026 | I41: FY2027 | J41: FY2028 | K41: FY2029 | L41: FY2030 | M41: FY2031 | N41: FY2032 | O41: FY2033
A42: Cash flow from operating activities | B42: -2892 | C42: 560 | D42: 660 | E42: -741 | F42: -3713 | G42: 2192 | H42: 5837
A43: Cash flow from investing activities | B43: 1877 | C43: -42 | D43: -1118 | E43: 1480 | F43: 1331 | G43: -2731 | H43: -3035
A44: Cash flow from financing activities | B44: 1622 | C44: -394 | D44: -329 | E44: 89 | F44: 2656 | G44: -857 | H44: -1806
A45: Net increase/(decrease) in cash | B45: =SUM(B42:B44) | C45: =SUM(C42:C44) | D45: =SUM(D42:D44) | E45: =SUM(E42:E44) | F45: =SUM(F42:F44) | G45: =SUM(G42:G44) | H45: =SUM(H42:H44)

Sheet Historical Ratio Analysis
A1: HISTORICAL RATIO ANALYSIS
A3: INR Crore | B3: FY2020 | C3: FY2021 | D3: FY2022 | E3: FY2023 | F3: FY2024 | G3: FY2025 | H3: FY2026 | I3: FY2027 | J3: FY2028 | K3: FY2029 | L3: FY2030 | M3: FY2031 | N3: FY2032 | O3: FY2033
A4: Growth & profitability
A5: Revenue growth % | C5: ='Historical Financial Statements'!C5/'Historical Financial Statements'!B5-1 | D5: ='Historical Financial Statements'!D5/'Historical Financial Statements'!C5-1 | E5: ='Historical Financial Statements'!E5/'Historical Financial Statements'!D5-1 | F5: ='Historical Financial Statements'!F5/'Historical Financial Statements'!E5-1 | G5: ='Historical Financial Statements'!G5/'Historical Financial Statements'!F5-1 | H5: ='Historical Financial Statements'!H5/'Historical Financial Statements'!G5-1
A6: Gross margin % | B6: ='Historical Financial Statements'!B7/'Historical Financial Statements'!B5 | C6: ='Historical Financial Statements'!C7/'Historical Financial Statements'!C5 | D6: ='Historical Financial Statements'!D7/'Historical Financial Statements'!D5 | E6: ='Historical Financial Statements'!E7/'Historical Financial Statements'!E5 | F6: ='Historical Financial Statements'!F7/'Historical Financial Statements'!F5 | G6: ='Historical Financial Statements'!G7/'Historical Financial Statements'!G5 | H6: ='Historical Financial Statements'!H7/'Historical Financial Statements'!H5
A7: EBITDA margin % | B7: ='Historical Financial Statements'!B12/'Historical Financial Statements'!B5 | C7: ='Historical Financial Statements'!C12/'Historical Financial Statements'!C5 | D7: ='Historical Financial Statements'!D12/'Historical Financial Statements'!D5 | E7: ='Historical Financial Statements'!E12/'Historical Financial Statements'!E5 | F7: ='Historical Financial Statements'!F12/'Historical Financial Statements'!F5 | G7: ='Historical Financial Statements'!G12/'Historical Financial Statements'!G5 | H7: ='Historical Financial Statements'!H12/'Historical Financial Statements'!H5
A8: EBIT margin % | B8: ='Historical Financial Statements'!B14/'Historical Financial Statements'!B5 | C8: ='Historical Financial Statements'!C14/'Historical Financial Statements'!C5 | D8: ='Historical Financial Statements'!D14/'Historical Financial Statements'!D5 | E8: ='Historical Financial Statements'!E14/'Historical Financial Statements'!E5 | F8: ='Historical Financial Statements'!F14/'Historical Financial Statements'!F5 | G8: ='Historical Financial Statements'!G14/'Historical Financial Statements'!G5 | H8: ='Historical Financial Statements'!H14/'Historical Financial Statements'!H5
A9: PAT margin % | B9: ='Historical Financial Statements'!B20/'Historical Financial Statements'!B5 | C9: ='Historical Financial Statements'!C20/'Historical Financial Statements'!C5 | D9: ='Historical Financial Statements'!D20/'Historical Financial Statements'!D5 | E9: ='Historical Financial Statements'!E20/'Historical Financial Statements'!E5 | F9: ='Historical Financial Statements'!F20/'Historical Financial Statements'!F5 | G9: ='Historical Financial Statements'!G20/'Historical Financial Statements'!G5 | H9: ='Historical Financial Statements'!H20/'Historical Financial Statements'!H5
A11: Returns
A12: ROE % | C12: ='Historical Financial Statements'!C20/(('Historical Financial Statements'!C33+'Historical Financial Statements'!C34+'Historical Financial Statements'!B33+'Historical Financial Statements'!B34)/2) | D12: ='Historical Financial Statements'!D20/(('Historical Financial Statements'!D33+'Historical Financial Statements'!D34+'Historical Financial Statements'!C33+'Historical Financial Statements'!C34)/2) | E12: ='Historical Financial Statements'!E20/(('Historical Financial Statements'!E33+'Historical Financial Statements'!E34+'Historical Financial Statements'!D33+'Historical Financial Statements'!D34)/2) | F12: ='Historical Financial Statements'!F20/(('Historical Financial Statements'!F33+'Historical Financial Statements'!F34+'Historical Financial Statements'!E33+'Historical Financial Statements'!E34)/2) | G12: ='Historical Financial Statements'!G20/(('Historical Financial Statements'!G33+'Historical Financial Statements'!G34+'Historical Financial Statements'!F33+'Historical Financial Statements'!F34)/2) | H12: ='Historical Financial Statements'!H20/(('Historical Financial Statements'!H33+'Historical Financial Statements'!H34+'Historical Financial Statements'!G33+'Historical Financial Statements'!G34)/2)
A13: ROCE % | B13: ='Historical Financial Statements'!B14/('Historical Financial Statements'!B33+'Historical Financial Statements'!B34+'Historical Financial Statements'!B35) | C13: ='Historical Financial Statements'!C14/('Historical Financial Statements'!C33+'Historical Financial Statements'!C34+'Historical Financial Statements'!C35) | D13: ='Historical Financial Statements'!D14/('Historical Financial Statements'!D33+'Historical Financial Statements'!D34+'Historical Financial Statements'!D35) | E13: ='Historical Financial Statements'!E14/('Historical Financial Statements'!E33+'Historical Financial Statements'!E34+'Historical Financial Statements'!E35) | F13: ='Historical Financial Statements'!F14/('Historical Financial Statements'!F33+'Historical Financial Statements'!F34+'Historical Financial Statements'!F35) | G13: ='Historical Financial Statements'!G14/('Historical Financial Statements'!G33+'Historical Financial Statements'!G34+'Historical Financial Statements'!G35) | H13: ='Historical Financial Statements'!H14/('Historical Financial Statements'!H33+'Historical Financial Statements'!H34+'Historical Financial Statements'!H35)
A14: ROA % | B14: ='Historical Financial Statements'!B20/'Historical Financial Statements'!B32 | C14: ='Historical Financial Statements'!C20/'Historical Financial Statements'!C32 | D14: ='Historical Financial Statements'!D20/'Historical Financial Statements'!D32 | E14: ='Historical Financial Statements'!E20/'Historical Financial Statements'!E32 | F14: ='Historical Financial Statements'!F20/'Historical Financial Statements'!F32 | G14: ='Historical Financial Statements'!G20/'Historical Financial Statements'!G32 | H14: ='Historical Financial Statements'!H20/'Historical Financial Statements'!H32
A16: Leverage & liquidity
A17: Debt / equity (x) | B17: ='Historical Financial Statements'!B35/('Historical Financial Statements'!B33+'Historical Financial Statements'!B34) | C17: ='Historical Financial Statements'!C35/('Historical Financial Statements'!C33+'Historical Financial Statements'!C34) | D17: ='Historical Financial Statements'!D35/('Historical Financial Statements'!D33+'Historical Financial Statements'!D34) | E17: ='Historical Financial Statements'!E35/('Historical Financial Statements'!E33+'Historical Financial Statements'!E34) | F17: ='Historical Financial Statements'!F35/('Historical Financial Statements'!F33+'Historical Financial Statements'!F34) | G17: ='Historical Financial Statements'!G35/('Historical Financial Statements'!G33+'Historical Financial Statements'!G34) | H17: ='Historical Financial Statements'!H35/('Historical Financial Statements'!H33+'Historical Financial Statements'!H34)
A18: Interest coverage (x) | B18: ='Historical Financial Statements'!B14/'Historical Financial Statements'!B16 | C18: ='Historical Financial Statements'!C14/'Historical Financial Statements'!C16 | D18: ='Historical Financial Statements'!D14/'Historical Financial Statements'!D16 | E18: ='Historical Financial Statements'!E14/'Historical Financial Statements'!E16 | F18: ='Historical Financial Statements'!F14/'Historical Financial Statements'!F16 | G18: ='Historical Financial Statements'!G14/'Historical Financial Statements'!G16 | H18: ='Historical Financial Statements'!H14/'Historical Financial Statements'!H16
A19: Asset turnover (x) | B19: ='Historical Financial Statements'!B5/'Historical Financial Statements'!B32 | C19: ='Historical Financial Statements'!C5/'Historical Financial Statements'!C32 | D19: ='Historical Financial Statements'!D5/'Historical Financial Statements'!D32 | E19: ='Historical Financial Statements'!E5/'Historical Financial Statements'!E32 | F19: ='Historical Financial Statements'!F5/'Historical Financial Statements'!F32 | G19: ='Historical Financial Statements'!G5/'Historical Financial Statements'!G32 | H19: ='Historical Financial Statements'!H5/'Historical Financial Statements'!H32
A21: Working capital (reported day ratios)
A22: Debtor days | B22: 121 | C22: 85 | D22: 52 | E22: 49 | F22: 73 | G22: 76 | H22: 73
A23: Inventory days | B23: 321 | C23: 333 | D23: 274 | E23: 261 | F23: 253 | G23: 289 | H23: 212
A24: Payable days | B24: 300 | C24: 281 | D24: 291 | E24: 345 | F24: 270 | G24: 259 | H24: 167
A25: Cash conversion cycle (days) | B25: 142 | C25: 137 | D25: 35 | E25: -35 | F25: 56 | G25: 106 | H25: 119

Sheet Operational Drivers
A1: OPERATIONAL DRIVERS
A2: Order data on standalone basis. FY20-22 figures are estimates (flagged). The "Adjustments" line captures order cancellations, de-scoping, FX revaluation, price/scope revisions and tax-basis differences so the roll ties to the reported closing order book.
A4: INR Crore | B4: FY2020 | C4: FY2021 | D4: FY2022 | E4: FY2023 | F4: FY2024 | G4: FY2025 | H4: FY2026 | I4: FY2027 | J4: FY2028 | K4: FY2029 | L4: FY2030 | M4: FY2031 | N4: FY2032 | O4: FY2033
A5: Order book dynamics (INR Crore, standalone)
A6: Opening order book | B6: 115000 | C6: 110000 | D6: 102000 | E6: 98000 | F6: 91336 | G6: 131598 | H6: 196328 | P6: FY20-22 est.
A7: Add: new order inflow | B7: 18000 | C7: 15000 | D7: 22000 | E7: 23548 | F7: 63000 | G7: 92535 | H7: 75000 | P7: some est.
A8: Less: revenue executed (standalone) | B8: -20495 | C8: -16296 | D8: -20153 | E8: -22136 | F8: -22921 | G8: -27355 | H8: -33782 | P8: standalone rev
A9: +/- Adjustments (cancellations, FX, scope, taxes) | B9: =B10-B6-B7-B8 | C9: =C10-C6-C7-C8 | D9: =D10-D6-D7-D8 | E9: =E10-E6-E7-E8 | F9: =F10-F6-F7-F8 | G9: =G10-G6-G7-G8 | H9: =H10-H6-H7-H8
A10: Closing order book (reported) | B10: 110000 | C10: 102000 | D10: 98000 | E10: 91336 | F10: 131598 | G10: 196328 | H10: 240000
A11: Roll check (open+inflow-rev+adj-close) | B11: =B6+B7+B8+B9-B10 | C11: =C6+C7+C8+C9-C10 | D11: =D6+D7+D8+D9-D10 | E11: =E6+E7+E8+E9-E10 | F11: =F6+F7+F8+F9-F10 | G11: =G6+G7+G8+G9-G10 | H11: =H6+H7+H8+H9-H10
A12: Book-to-bill (closing OB / revenue, x) | B12: =B10/-B8 | C12: =C10/-C8 | D12: =D10/-D8 | E12: =E10/-E8 | F12: =F10/-F8 | G12: =G10/-G8 | H12: =H10/-H8
A13: Execution rate (revenue / opening OB) | B13: =-B8/B6 | C13: =-C8/C6 | D13: =-D8/D6 | E13: =-E8/E6 | F13: =-F8/F6 | G13: =-G8/G6 | H13: =-H8/H6
A15: Segment revenue mix (INR Crore, est.)
A16: Power segment | B16: 16800 | C16: 13500 | D16: 16500 | E16: 18100 | F16: 18600 | G16: 20937 | H16: 25407
A17: Industry segment | B17: 3900 | C17: 3200 | D17: 4000 | E17: 4600 | F17: 4700 | G17: 6400 | H17: 7400
A18: Others / exports / renewables | B18: 763 | C18: 609 | D18: 711 | E18: 665 | F18: 593 | G18: 1002 | H18: 975
A19: Total (check vs revenue) | B19: =SUM(B16:B18) | C19: =SUM(C16:C18) | D19: =SUM(D16:D18) | E19: =SUM(E16:E18) | F19: =SUM(F16:F18) | G19: =SUM(G16:G18) | H19: =SUM(H16:H18)
A20: Power as % of revenue | B20: =B16/'Historical Financial Statements'!B5 | C20: =C16/'Historical Financial Statements'!C5 | D20: =D16/'Historical Financial Statements'!D5 | E20: =E16/'Historical Financial Statements'!E5 | F20: =F16/'Historical Financial Statements'!F5 | G20: =G16/'Historical Financial Statements'!G5 | H20: =H16/'Historical Financial Statements'!H5
A22: Other KPIs
A23: Approx. workforce (number) | B23: 33500 | C23: 31500 | D23: 29800 | E23: 28500 | F23: 27000 | G23: 26000 | H23: 25500 | P23: approx.
A24: R&D expenditure | B24: 1180 | C24: 1090 | D24: 1050 | E24: 1100 | F24: 1150 | G24: 1300 | H24: 1500 | P24: approx.
A25: R&D as % of revenue | B25: =B24/'Historical Financial Statements'!B5 | C25: =C24/'Historical Financial Statements'!C5 | D25: =D24/'Historical Financial Statements'!D5 | E25: =E24/'Historical Financial Statements'!E5 | F25: =F24/'Historical Financial Statements'!F5 | G25: =G24/'Historical Financial Statements'!G5 | H25: =H24/'Historical Financial Statements'!H5
A26: Capacity utilisation (mfg.) | B26: 0.55 | C26: 0.42 | D26: 0.5 | E26: 0.55 | F26: 0.58 | G26: 0.65 | H26: 0.72 | P26: approx.

Sheet Revenue Build-up
A1: REVENUE BUILD-UP
A2: Order book rolled on STANDALONE basis: Closing OB = Opening + Inflow - Standalone revenue + Adjustments (cancellations/FX/scope/taxes). Consolidated revenue (P&L) is bridged from standalone via a consolidation uplift.
A4: INR Crore | B4: FY2020 | C4: FY2021 | D4: FY2022 | E4: FY2023 | F4: FY2024 | G4: FY2025 | H4: FY2026 | I4: FY2027 | J4: FY2028 | K4: FY2029 | L4: FY2030 | M4: FY2031 | N4: FY2032 | O4: FY2033
A5: A. Order book roll-forward (standalone basis, as disclosed)
A6: Opening order book (standalone) | B6: ='Operational Drivers'!B6 | C6: ='Operational Drivers'!C6 | D6: ='Operational Drivers'!D6 | E6: ='Operational Drivers'!E6 | F6: ='Operational Drivers'!F6 | G6: ='Operational Drivers'!G6 | H6: ='Operational Drivers'!H6 | I6: ='Operational Drivers'!H10 | J6: =I10 | K6: =J10 | L6: =K10 | M6: =L10 | N6: =M10 | O6: =N10
A7: Add: new order inflow | B7: ='Operational Drivers'!B7 | C7: ='Operational Drivers'!C7 | D7: ='Operational Drivers'!D7 | E7: ='Operational Drivers'!E7 | F7: ='Operational Drivers'!F7 | G7: ='Operational Drivers'!G7 | H7: ='Operational Drivers'!H7 | I7: ='Assumptions'!I5 | J7: ='Assumptions'!J5 | K7: ='Assumptions'!K5 | L7: ='Assumptions'!L5 | M7: ='Assumptions'!M5 | N7: ='Assumptions'!N5 | O7: ='Assumptions'!O5
A8: Less: standalone revenue executed | B8: ='Operational Drivers'!B8 | C8: ='Operational Drivers'!C8 | D8: ='Operational Drivers'!D8 | E8: ='Operational Drivers'!E8 | F8: ='Operational Drivers'!F8 | G8: ='Operational Drivers'!G8 | H8: ='Operational Drivers'!H8 | I8: =-'Assumptions'!I10*I6 | J8: =-'Assumptions'!J10*J6 | K8: =-'Assumptions'!K10*K6 | L8: =-'Assumptions'!L10*L6 | M8: =-'Assumptions'!M10*M6 | N8: =-'Assumptions'!N10*N6 | O8: =-'Assumptions'!O10*O6
A9: +/- Adjustments (cancellations/FX/scope/taxes) | B9: ='Operational Drivers'!B9 | C9: ='Operational Drivers'!C9 | D9: ='Operational Drivers'!D9 | E9: ='Operational Drivers'!E9 | F9: ='Operational Drivers'!F9 | G9: ='Operational Drivers'!G9 | H9: ='Operational Drivers'!H9 | I9: 0 | J9: 0 | K9: 0 | L9: 0 | M9: 0 | N9: 0 | O9: 0
A10: Closing order book (standalone) | B10: =B6+B7+B8+B9 | C10: =C6+C7+C8+C9 | D10: =D6+D7+D8+D9 | E10: =E6+E7+E8+E9 | F10: =F6+F7+F8+F9 | G10: =G6+G7+G8+G9 | H10: =H6+H7+H8+H9 | I10: =I6+I7+I8+I9 | ... O10: =O6+O7+O8+O9
A12: B. Standalone -> consolidated revenue bridge
A13: Standalone revenue from operations | B13: =-B8 | C13: =-C8 | D13: =-D8 | E13: =-E8 | F13: =-F8 | G13: =-G8 | H13: =-H8 | I13: =-I8 | ... O13: =-O8
A14: Consolidation uplift % (consol/standalone - 1) | B14: ='Historical Financial Statements'!B5/B13-1 | C14: ='Historical Financial Statements'!C5/C13-1 | D14: ='Historical Financial Statements'!D5/D13-1 | E14: ='Historical Financial Statements'!E5/E13-1 | F14: ='Historical Financial Statements'!F5/F13-1 | G14: ='Historical Financial Statements'!G5/G13-1 | H14: ='Historical Financial Statements'!H5/H13-1 | I14: ='Assumptions'!I22 | J14: ='Assumptions'!J22 | K14: ='Assumptions'!K22 | L14: ='Assumptions'!L22 | M14: ='Assumptions'!M22 | N14: ='Assumptions'!N22 | O14: ='Assumptions'!O22
A15: Consolidated revenue from operations -> P&L | B15: =B13*(1+B14) | C15: =C13*(1+C14) | D15: =D13*(1+D14) | E15: =E13*(1+E14) | F15: =F13*(1+F14) | G15: =G13*(1+G14) | H15: =H13*(1+H14) | I15: =I13*(1+I14) | ... O15: =O13*(1+O14)
A16: Revenue growth % (consolidated) | C16: =C15/B15-1 | D16: =D15/C15-1 | E16: =E15/D15-1 | F16: =F15/E15-1 | G16: =G15/F15-1 | H16: =H15/G15-1 | I16: =I15/H15-1 | J16: =J15/I15-1 | ... O16: =O15/N15-1
A17: Execution rate % (standalone rev / opening OB) | B17: =B13/B6 | C17: =C13/C6 | D17: =D13/D6 | E17: =E13/E6 | F17: =F13/F6 | G17: =G13/G6 | H17: =H13/H6 | I17: =I13/I6 | ... O17: =O13/O6
A18: Book-to-bill (closing OB / standalone rev, x) | B18: =B10/B13 | C18: =C10/C13 | D18: =D10/D13 | E18: =E10/E13 | F18: =F10/F13 | G18: =G10/G13 | H18: =H10/H13 | I18: =I10/I13 | ... O18: =O10/O13
A20: C. Segment revenue breakup (consolidated)
A21: Power segment | B21: ='Operational Drivers'!B16 | C21: ='Operational Drivers'!C16 | D21: ='Operational Drivers'!D16 | E21: ='Operational Drivers'!E16 | F21: ='Operational Drivers'!F16 | G21: ='Operational Drivers'!G16 | H21: ='Operational Drivers'!H16 | I21: =I15*'Assumptions'!I33 | J21: =J15*'Assumptions'!J33 | K21: =K15*'Assumptions'!K33 | L21: =L15*'Assumptions'!L33 | M21: =M15*'Assumptions'!M33 | N21: =N15*'Assumptions'!N33 | O21: =O15*'Assumptions'!O33
A22: Industry segment | B22: ='Operational Drivers'!B17 | C22: ='Operational Drivers'!C17 | D22: ='Operational Drivers'!D17 | E22: ='Operational Drivers'!E17 | F22: ='Operational Drivers'!F17 | G22: ='Operational Drivers'!G17 | H22: ='Operational Drivers'!H17 | I22: =I15*'Assumptions'!I34 | J22: =J15*'Assumptions'!J34 | K22: =K15*'Assumptions'!K34 | L22: =L15*'Assumptions'!L34 | M22: =M15*'Assumptions'!M34 | N22: =N15*'Assumptions'!N34 | O22: =O15*'Assumptions'!O34
A23: Others / exports / renewables | B23: ='Operational Drivers'!B18 | C23: ='Operational Drivers'!C18 | D23: ='Operational Drivers'!D18 | E23: ='Operational Drivers'!E18 | F23: ='Operational Drivers'!F18 | G23: ='Operational Drivers'!G18 | H23: ='Operational Drivers'!H18 | I23: =I15*(1-'Assumptions'!I33-'Assumptions'!I34) | J23: =J15*(1-'Assumptions'!J33-'Assumptions'!J34) | K23: =K15*(1-'Assumptions'!K33-'Assumptions'!K34) | L23: =L15*(1-'Assumptions'!L33-'Assumptions'!L34) | M23: =M15*(1-'Assumptions'!M33-'Assumptions'!M34) | N23: =N15*(1-'Assumptions'!N33-'Assumptions'!N34) | O23: =O15*(1-'Assumptions'!O33-'Assumptions'!O34)
A24: Total segment revenue (check vs consolidated) | B24: =SUM(B21:B23) | C24: =SUM(C21:C23) | D24: =SUM(D21:D23) | E24: =SUM(E21:E23) | F24: =SUM(F21:F23) | G24: =SUM(G21:G23) | H24: =SUM(H21:H23) | I24: =SUM(I21:I23) | ... O24: =SUM(O21:O23)

Sheet Cost Forecast
A1: COST FORECAST
A2: Granular cost build-up. COGS = materials (steel/copper/components/imported/other) + subcontracting. OpEx = employee + selling + admin + R&D. EBITDA = revenue x target margin. Historical sub-components are not separately disclosed (shown at total level).
A4: INR Crore | B4: FY2020 | C4: FY2021 | D4: FY2022 | E4: FY2023 | F4: FY2024 | G4: FY2025 | H4: FY2026 | I4: FY2027 | J4: FY2028 | K4: FY2029 | L4: FY2030 | M4: FY2031 | N4: FY2032 | O4: FY2033
A5: A. Cost of goods sold (COGS)
A6: Revenue from operations | B6: ='Historical Financial Statements'!B5 | C6: ='Historical Financial Statements'!C5 | D6: ='Historical Financial Statements'!D5 | E6: ='Historical Financial Statements'!E5 | F6: ='Historical Financial Statements'!F5 | G6: ='Historical Financial Statements'!G5 | H6: ='Historical Financial Statements'!H5 | I6: ='Revenue Build-up'!I15 | J6: ='Revenue Build-up'!J15 | K6: ='Revenue Build-up'!K15 | L6: ='Revenue Build-up'!L15 | M6: ='Revenue Build-up'!M15 | N6: ='Revenue Build-up'!N15 | O6: ='Revenue Build-up'!O15
A7: Steel | I7: =I6*'Assumptions'!I27 | J7: =J6*'Assumptions'!J27 | K7: =K6*'Assumptions'!K27 | L7: =L6*'Assumptions'!L27 | M7: =M6*'Assumptions'!M27 | N7: =N6*'Assumptions'!N27 | O7: =O6*'Assumptions'!O27
A8: Copper | I8: =I6*'Assumptions'!I28 | J8: =J6*'Assumptions'!J28 | K8: =K6*'Assumptions'!K28 | L8: =L6*'Assumptions'!L28 | M8: =M6*'Assumptions'!M28 | N8: =N6*'Assumptions'!N28 | O8: =O6*'Assumptions'!O28
A9: Electrical & electronic components | I9: =I6*'Assumptions'!I29 | J9: =J6*'Assumptions'!J29 | K9: =K6*'Assumptions'!K29 | L9: =L6*'Assumptions'!L29 | M9: =M6*'Assumptions'!M29 | N9: =N6*'Assumptions'!N29 | O9: =O6*'Assumptions'!O29
A10: Imported components | I10: =I6*'Assumptions'!I30 | J10: =J6*'Assumptions'!J30 | K10: =K6*'Assumptions'!K30 | L10: =L6*'Assumptions'!L30 | M10: =M6*'Assumptions'!M30 | N10: =N6*'Assumptions'!N30 | O10: =O6*'Assumptions'!O30
A11: Other materials & consumables | I11: =I6*(1-'Assumptions'!I15-'Assumptions'!I24-'Assumptions'!I25-'Assumptions'!I26-'Assumptions'!I27-'Assumptions'!I28-'Assumptions'!I29-'Assumptions'!I30) | J11: =J6*(1-'Assumptions'!J15-'Assumptions'!J24-'Assumptions'!J25-'Assumptions'!J26-'Assumptions'!J27-'Assumptions'!J28-'Assumptions'!J29-'Assumptions'!J30) | K11: =K6*(1-'Assumptions'!K15-'Assumptions'!K24-'Assumptions'!K25-'Assumptions'!K26-'Assumptions'!K27-'Assumptions'!K28-'Assumptions'!K29-'Assumptions'!K30) | L11: =L6*(1-'Assumptions'!L15-'Assumptions'!L24-'Assumptions'!L25-'Assumptions'!L26-'Assumptions'!L27-'Assumptions'!L28-'Assumptions'!L29-'Assumptions'!L30) | M11: =M6*(1-'Assumptions'!M15-'Assumptions'!M24-'Assumptions'!M25-'Assumptions'!M26-'Assumptions'!M27-'Assumptions'!M28-'Assumptions'!M29-'Assumptions'!M30) | N11: =N6*(1-'Assumptions'!N15-'Assumptions'!N24-'Assumptions'!N25-'Assumptions'!N26-'Assumptions'!N27-'Assumptions'!N28-'Assumptions'!N29-'Assumptions'!N30) | O11: =O6*(1-'Assumptions'!O15-'Assumptions'!O24-'Assumptions'!O25-'Assumptions'!O26-'Assumptions'!O27-'Assumptions'!O28-'Assumptions'!O29-'Assumptions'!O30)
A12: Subcontracting & erection | I12: =I6*'Assumptions'!I25 | J12: =J6*'Assumptions'!J25 | K12: =K6*'Assumptions'!K25 | L12: =L6*'Assumptions'!L25 | M12: =M6*'Assumptions'!M25 | N12: =N6*'Assumptions'!N25 | O12: =O6*'Assumptions'!O25
A13: Total COGS | B13: ='Historical Financial Statements'!B6 | C13: ='Historical Financial Statements'!C6 | D13: ='Historical Financial Statements'!D6 | E13: ='Historical Financial Statements'!E6 | F13: ='Historical Financial Statements'!F6 | G13: ='Historical Financial Statements'!G6 | H13: ='Historical Financial Statements'!H6 | I13: =SUM(I7:I12) | J13: =SUM(J7:J12) | K13: =SUM(K7:K12) | L13: =SUM(L7:L12) | M13: =SUM(M7:M12) | N13: =SUM(N7:N12) | O13: =SUM(O7:O12)
A14: Gross profit | B14: ='Historical Financial Statements'!B7 | C14: ='Historical Financial Statements'!C7 | D14: ='Historical Financial Statements'!D7 | E14: ='Historical Financial Statements'!E7 | F14: ='Historical Financial Statements'!F7 | G14: ='Historical Financial Statements'!G7 | H14: ='Historical Financial Statements'!H7 | I14: =I6-I13 | J14: =J6-J13 | K14: =K6-K13 | L14: =L6-L13 | M14: =M6-M13 | N14: =N6-N13 | O14: =O6-O13
A15: B. Operating expenses
A16: Employee cost | B16: ='Historical Financial Statements'!B9 | C16: ='Historical Financial Statements'!C9 | D16: ='Historical Financial Statements'!D9 | E16: ='Historical Financial Statements'!E9 | F16: ='Historical Financial Statements'!F9 | G16: ='Historical Financial Statements'!G9 | H16: ='Historical Financial Statements'!H9 | I16: =I6*'Assumptions'!I24 | J16: =J6*'Assumptions'!J24 | K16: =K6*'Assumptions'!K24 | L16: =L6*'Assumptions'!L24 | M16: =M6*'Assumptions'!M24 | N16: =N6*'Assumptions'!N24 | O16: =O6*'Assumptions'!O24
A17: Selling & distribution | I17: =I6*'Assumptions'!I31 | J17: =J6*'Assumptions'!J31 | K17: =K6*'Assumptions'!K31 | L17: =L6*'Assumptions'!L31 | M17: =M6*'Assumptions'!M31 | N17: =N6*'Assumptions'!N31 | O17: =O6*'Assumptions'!O31
A18: Administrative expenses | I18: =I6*('Assumptions'!I26-'Assumptions'!I31-'Assumptions'!I32) | J18: =J6*('Assumptions'!J26-'Assumptions'!J31-'Assumptions'!J32) | K18: =K6*('Assumptions'!K26-'Assumptions'!K31-'Assumptions'!K32) | L18: =L6*('Assumptions'!L26-'Assumptions'!L31-'Assumptions'!L32) | M18: =M6*('Assumptions'!M26-'Assumptions'!M31-'Assumptions'!M32) | N18: =N6*('Assumptions'!N26-'Assumptions'!N31-'Assumptions'!N32) | O18: =O6*('Assumptions'!O26-'Assumptions'!O31-'Assumptions'!O32)
A19: Research & development | I19: =I6*'Assumptions'!I32 | J19: =J6*'Assumptions'!J32 | K19: =K6*'Assumptions'!K32 | L19: =L6*'Assumptions'!L32 | M19: =M6*'Assumptions'!M32 | N19: =N6*'Assumptions'!N32 | O19: =O6*'Assumptions'!O32
A20: Selling, admin & R&D | B20: ='Historical Financial Statements'!B10 | C20: ='Historical Financial Statements'!C10 | D20: ='Historical Financial Statements'!D10 | E20: ='Historical Financial Statements'!E10 | F20: ='Historical Financial Statements'!F10 | G20: ='Historical Financial Statements'!G10 | H20: ='Historical Financial Statements'!H10 | I20: =SUM(I17:I19) | J20: =SUM(J17:J19) | K20: =SUM(K17:K19) | L20: =SUM(L17:L19) | M20: =SUM(M17:M19) | N20: =SUM(N17:N19) | O20: =SUM(O17:O19)
A21: Total operating expenses | B21: ='Historical Financial Statements'!B11 | C21: ='Historical Financial Statements'!C11 | D21: ='Historical Financial Statements'!D11 | E21: ='Historical Financial Statements'!E11 | F21: ='Historical Financial Statements'!F11 | G21: ='Historical Financial Statements'!G11 | H21: ='Historical Financial Statements'!H11 | I21: =I16+I20 | J21: =J16+J20 | K21: =K16+K20 | L21: =L16+L20 | M21: =M16+M20 | N21: =N16+N20 | O21: =O16+O20
A22: EBITDA | B22: ='Historical Financial Statements'!B12 | C22: ='Historical Financial Statements'!C12 | D22: ='Historical Financial Statements'!D12 | E22: ='Historical Financial Statements'!E12 | F22: ='Historical Financial Statements'!F12 | G22: ='Historical Financial Statements'!G12 | H22: ='Historical Financial Statements'!H12 | I22: =I14-I21 | J22: =J14-J21 | K22: =K14-K21 | L22: =L14-L21 | M22: =M14-M21 | N22: =N14-N21 | O22: =O14-O21
A23: EBITDA margin % | B23: =B22/B6 | C23: =C22/C6 | D23: =D22/D6 | E23: =E22/E6 | F23: =F22/F6 | G23: =G22/G6 | H23: =H22/H6 | I23: =I22/I6 | ... O23: =O22/O6
A24: Memo: total operating cost (COGS+OpEx) | B24: ='Historical Financial Statements'!B23 | C24: ='Historical Financial Statements'!C23 | D24: ='Historical Financial Statements'!D23 | E24: ='Historical Financial Statements'!E23 | F24: ='Historical Financial Statements'!F23 | G24: ='Historical Financial Statements'!G23 | H24: ='Historical Financial Statements'!H23 | I24: =I13+I21 | J24: =J13+J21 | K24: =K13+K21 | L24: =L13+L21 | M24: =M13+M21 | N24: =N13+N21 | O24: =O13+O21

Sheet Working Capital Schedule
A1: WORKING CAPITAL SCHEDULE
A2: Granular operating working capital (current & non-current). FY26 = audited seed; FY27-33 driven by Assumptions.
A4: INR Crore | B4: FY2020 | C4: FY2021 | D4: FY2022 | E4: FY2023 | F4: FY2024 | G4: FY2025 | H4: FY2026 | I4: FY2027 | J4: FY2028 | K4: FY2029 | L4: FY2030 | M4: FY2031 | N4: FY2032 | O4: FY2033
A5: Operating working capital
A6: Revenue from operations | I6: ='Cost Forecast'!I6 | J6: ='Cost Forecast'!J6 | K6: ='Cost Forecast'!K6 | L6: ='Cost Forecast'!L6 | M6: ='Cost Forecast'!M6 | N6: ='Cost Forecast'!N6 | O6: ='Cost Forecast'!O6
A7: Cost of sales (total operating cost) | I7: ='Cost Forecast'!I24 | J7: ='Cost Forecast'!J24 | K7: ='Cost Forecast'!K24 | L7: ='Cost Forecast'!L24 | M7: ='Cost Forecast'!M24 | N7: ='Cost Forecast'!N24 | O7: ='Cost Forecast'!O24
A8: Trade receivables - current | H8: 6796.27 | I8: ='Assumptions'!I72*I6 | J8: ='Assumptions'!J72*J6 | K8: ='Assumptions'!K72*K6 | L8: ='Assumptions'!L72*L6 | M8: ='Assumptions'!M72*M6 | N8: ='Assumptions'!N72*N6 | O8: ='Assumptions'!O72*O6
A9: Trade receivables - non-current | H9: 2426.93 | I9: ='Assumptions'!I73*I6 | J9: ='Assumptions'!J73*J6 | K9: ='Assumptions'!K73*K6 | L9: ='Assumptions'!L73*L6 | M9: ='Assumptions'!M73*M6 | N9: ='Assumptions'!N73*N6 | O9: ='Assumptions'!O73*O6
A10: Inventories | H10: 13334.58 | I10: ='Assumptions'!I74*I6 | J10: ='Assumptions'!J74*J6 | K10: ='Assumptions'!K74*K6 | L10: ='Assumptions'!L74*L6 | M10: ='Assumptions'!M74*M6 | N10: ='Assumptions'!N74*N6 | O10: ='Assumptions'!O74*O6
A11: Contract assets - current | H11: 15192.89 | I11: ='Assumptions'!I75*I6 | J11: ='Assumptions'!J75*J6 | K11: ='Assumptions'!K75*K6 | L11: ='Assumptions'!L75*L6 | M11: ='Assumptions'!M75*M6 | N11: ='Assumptions'!N75*N6 | O11: ='Assumptions'!O75*O6
A12: Contract assets - non-current | H12: 14196.72 | I12: ='Assumptions'!I76*I6 | J12: ='Assumptions'!J76*J6 | K12: ='Assumptions'!K76*K6 | L12: ='Assumptions'!L76*L6 | M12: ='Assumptions'!M76*M6 | N12: ='Assumptions'!N76*N6 | O12: ='Assumptions'!O76*O6
A13: Deferred tax assets | H13: 3532.8 | I13: =H13 | J13: =I13 | K13: =J13 | L13: =K13 | M13: =L13 | N13: =M13 | O13: =N13
A14: Other current assets (residual) | H14: 4264.99 | I14: ='Assumptions'!I78*I6 | J14: ='Assumptions'!J78*J6 | K14: ='Assumptions'!K78*K6 | L14: ='Assumptions'!L78*L6 | M14: ='Assumptions'!M78*M6 | N14: ='Assumptions'!N78*N6 | O14: ='Assumptions'!O78*O6
A15: Other non-current assets (residual) | H15: 778.17 | I15: =H15*(1+'Assumptions'!I79) | J15: =I15*(1+'Assumptions'!J79) | K15: =J15*(1+'Assumptions'!K79) | L15: =K15*(1+'Assumptions'!L79) | M15: =L15*(1+'Assumptions'!M79) | N15: =M15*(1+'Assumptions'!N79) | O15: =N15*(1+'Assumptions'!O79)
A16: Total operating assets | H16: =SUM(H8:H15) | I16: =SUM(I8:I15) | J16: =SUM(J8:J15) | K16: =SUM(K8:K15) | L16: =SUM(L8:L15) | M16: =SUM(M8:M15) | N16: =SUM(N8:N15) | O16: =SUM(O8:O15)
A17: Trade payables - current | H17: 10491.6 | I17: ='Assumptions'!I80*I6 | J17: ='Assumptions'!J80*J6 | K17: ='Assumptions'!K80*K6 | L17: ='Assumptions'!L80*L6 | M17: ='Assumptions'!M80*M6 | N17: ='Assumptions'!N80*N6 | O17: ='Assumptions'!O80*O6
A18: Trade payables - non-current | H18: 1343.44 | I18: =H18 | J18: =I18 | K18: =J18 | L18: =K18 | M18: =L18 | N18: =M18 | O18: =N18
A19: Contract liabilities - current | H19: 9110.39 | I19: ='Assumptions'!I82*I6 | J19: ='Assumptions'!J82*J6 | K19: ='Assumptions'!K82*K6 | L19: ='Assumptions'!L82*L6 | M19: ='Assumptions'!M82*M6 | N19: ='Assumptions'!N82*N6 | O19: ='Assumptions'!O82*O6
A20: Contract liabilities - non-current | H20: 13413.24 | I20: ='Assumptions'!I83*I6 | J20: ='Assumptions'!J83*J6 | K20: ='Assumptions'!K83*K6 | L20: ='Assumptions'!L83*L6 | M20: ='Assumptions'!M83*M6 | N20: ='Assumptions'!N83*N6 | O20: ='Assumptions'!O83*O6
A21: Provisions - current | H21: 1918.91 | I21: ='Assumptions'!I84*I6 | J21: ='Assumptions'!J84*J6 | K21: ='Assumptions'!K84*K6 | L21: ='Assumptions'!L84*L6 | M21: ='Assumptions'!M84*M6 | N21: ='Assumptions'!N84*N6 | O21: ='Assumptions'!O84*O6
A22: Long-term provisions | H22: 2354.62 | I22: =H22*(1+'Assumptions'!I85) | J22: =I22*(1+'Assumptions'!J85) | K22: =J22*(1+'Assumptions'!K85) | L22: =K22*(1+'Assumptions'!L85) | M22: =L22*(1+'Assumptions'!M85) | N22: =M22*(1+'Assumptions'!N85) | O22: =N22*(1+'Assumptions'!O85)
A23: Other current liabilities (residual) | H23: 2762.51 | I23: ='Assumptions'!I86*I6 | J23: ='Assumptions'!J86*J6 | K23: ='Assumptions'!K86*K6 | L23: ='Assumptions'!L86*L6 | M23: ='Assumptions'!M86*M6 | N23: ='Assumptions'!N86*N6 | O23: ='Assumptions'!O86*O6
A24: Other non-current liabilities (residual) | H24: 457.35 | I24: =H24*(1+'Assumptions'!I87) | J24: =I24*(1+'Assumptions'!J87) | K24: =J24*(1+'Assumptions'!K87) | L24: =K24*(1+'Assumptions'!L87) | M24: =L24*(1+'Assumptions'!M87) | N24: =M24*(1+'Assumptions'!N87) | O24: =N24*(1+'Assumptions'!O87)
A25: Total operating liabilities | H25: =SUM(H17:H24) | I25: =SUM(I17:I24) | J25: =SUM(J17:J24) | K25: =SUM(K17:K24) | L25: =SUM(L17:L24) | M25: =SUM(M17:M24) | N25: =SUM(N17:N24) | O25: =SUM(O17:O24)
A26: Net working capital | H26: =H16-H25 | I26: =I16-I25 | J26: =J16-J25 | K26: =K16-K25 | L26: =L16-L25 | M26: =M16-M25 | N26: =N16-N25 | O26: =O16-O25
A27: (Increase)/decrease in NWC | I27: =-(I26-H26) | J27: =-(J26-I26) | K27: =-(K26-J26) | L27: =-(L26-K26) | M27: =-(M26-L26) | N27: =-(N26-M26) | O27: =-(O26-N26)

Sheet Fixed Asset Schedule
A1: FIXED ASSET SCHEDULE
A2: Net-block roll-forward. Opening FY27 = reported FY26 net PPE. Depreciation = rate x opening net block.
A4: INR Crore | B4: FY2020 | C4: FY2021 | D4: FY2022 | E4: FY2023 | F4: FY2024 | G4: FY2025 | H4: FY2026 | I4: FY2027 | J4: FY2028 | K4: FY2029 | L4: FY2030 | M4: FY2031 | N4: FY2032 | O4: FY2033
A5: Net block roll-forward
A6: Opening net block | B6: ='Historical Financial Statements'!B28 | C6: ='Historical Financial Statements'!C28 | D6: ='Historical Financial Statements'!D28 | E6: ='Historical Financial Statements'!E28 | F6: ='Historical Financial Statements'!F28 | G6: ='Historical Financial Statements'!G28 | H6: ='Historical Financial Statements'!H28 | I6: ='Forecast Financial Statements'!H53 | J6: =I10 | K6: =J10 | L6: =K10 | M6: =L10 | N6: =M10 | O6: =N10
A7: Add: capital expenditure | I7: ='Assumptions'!I35 | J7: ='Assumptions'!J35 | K7: ='Assumptions'!K35 | L7: ='Assumptions'!L35 | M7: ='Assumptions'!M35 | N7: ='Assumptions'!N35 | O7: ='Assumptions'!O35
A8: Less: depreciation | I8: =-'Assumptions'!I36*I6 | J8: =-'Assumptions'!J36*J6 | K8: =-'Assumptions'!K36*K6 | L8: =-'Assumptions'!L36*L6 | M8: =-'Assumptions'!M36*M6 | N8: =-'Assumptions'!N36*N6 | O8: =-'Assumptions'!O36*O6
A9: Less: disposals | I9: 0 | J9: 0 | K9: 0 | L9: 0 | M9: 0 | N9: 0 | O9: 0
A10: Closing net block | B10: ='Historical Financial Statements'!B28 | C10: ='Historical Financial Statements'!C28 | D10: ='Historical Financial Statements'!D28 | E10: ='Historical Financial Statements'!E28 | F10: ='Historical Financial Statements'!F28 | G10: ='Historical Financial Statements'!G28 | H10: ='Historical Financial Statements'!H28 | I10: =I6+I7+I8-I9 | J10: =J6+J7+J8-J9 | K10: =K6+K7+K8-K9 | L10: =L6+L7+L8-L9 | M10: =M6+M7+M8-M9 | N10: =N6+N7+N8-N9 | O10: =O6+O7+O8-O9

Sheet Depreciation Schedule
A1: DEPRECIATION SCHEDULE
A4: INR Crore | B4: FY2020 | C4: FY2021 | D4: FY2022 | E4: FY2023 | F4: FY2024 | G4: FY2025 | H4: FY2026 | I4: FY2027 | J4: FY2028 | K4: FY2029 | L4: FY2030 | M4: FY2031 | N4: FY2032 | O4: FY2033
A5: Depreciation computation
A6: Opening net block | I6: ='Fixed Asset Schedule'!I6 | J6: ='Fixed Asset Schedule'!J6 | K6: ='Fixed Asset Schedule'!K6 | L6: ='Fixed Asset Schedule'!L6 | M6: ='Fixed Asset Schedule'!M6 | N6: ='Fixed Asset Schedule'!N6 | O6: ='Fixed Asset Schedule'!O6
A7: Depreciation rate % | I7: ='Assumptions'!I36 | J7: ='Assumptions'!J36 | K7: ='Assumptions'!K36 | L7: ='Assumptions'!L36 | M7: ='Assumptions'!M36 | N7: ='Assumptions'!N36 | O7: ='Assumptions'!O36
A8: Depreciation expense | B8: ='Historical Financial Statements'!B13 | C8: ='Historical Financial Statements'!C13 | D8: ='Historical Financial Statements'!D13 | E8: ='Historical Financial Statements'!E13 | F8: ='Historical Financial Statements'!F13 | G8: ='Historical Financial Statements'!G13 | H8: ='Historical Financial Statements'!H13 | I8: =I6*I7 | J8: =J6*J7 | K8: =K6*K7 | L8: =L6*L7 | M8: =M6*M7 | N8: =N6*N7 | O8: =O6*O7

Sheet Debt Schedule
A1: DEBT SCHEDULE
A2: Interest on opening debt (no circularity). Opening FY27 = reported FY26 borrowings.
A4: INR Crore | B4: FY2020 | C4: FY2021 | D4: FY2022 | E4: FY2023 | F4: FY2024 | G4: FY2025 | H4: FY2026 | I4: FY2027 | J4: FY2028 | K4: FY2029 | L4: FY2030 | M4: FY2031 | N4: FY2032 | O4: FY2033
A5: Debt roll-forward
A6: Opening debt | B6: ='Historical Financial Statements'!B35 | C6: ='Historical Financial Statements'!C35 | D6: ='Historical Financial Statements'!D35 | E6: ='Historical Financial Statements'!E35 | F6: ='Historical Financial Statements'!F35 | G6: ='Historical Financial Statements'!G35 | H6: ='Historical Financial Statements'!H35 | I6: ='Forecast Financial Statements'!H72 | J6: =I9 | K6: =J9 | L6: =K9 | M6: =L9 | N6: =M9 | O6: =N9
A7: Add: new borrowings | I7: ='Assumptions'!I48 | J7: ='Assumptions'!J48 | K7: ='Assumptions'!K48 | L7: ='Assumptions'!L48 | M7: ='Assumptions'!M48 | N7: ='Assumptions'!N48 | O7: ='Assumptions'!O48
A8: Less: repayments | I8: =-'Assumptions'!I49 | J8: =-'Assumptions'!J49 | K8: =-'Assumptions'!K49 | L8: =-'Assumptions'!L49 | M8: =-'Assumptions'!M49 | N8: =-'Assumptions'!N49 | O8: =-'Assumptions'!O49
A9: Closing debt | B9: ='Historical Financial Statements'!B35 | C9: ='Historical Financial Statements'!C35 | D9: ='Historical Financial Statements'!D35 | E9: ='Historical Financial Statements'!E35 | F9: ='Historical Financial Statements'!F35 | G9: ='Historical Financial Statements'!G35 | H9: ='Historical Financial Statements'!H35 | I9: =I6+I7+I8 | J9: =J6+J7+J8 | K9: =K6+K7+K8 | L9: =L6+L7+L8 | M9: =M6+M7+M8 | N9: =N6+N7+N8 | O9: =O6+O7+O8
A10: Average debt | I10: =(I6+I9)/2 | J10: =(J6+J9)/2 | K10: =(K6+K9)/2 | L10: =(L6+L9)/2 | M10: =(M6+M9)/2 | N10: =(N6+N9)/2 | O10: =(O6+O9)/2
A11: Interest expense (on opening debt) | B11: ='Historical Financial Statements'!B16 | C11: ='Historical Financial Statements'!C16 | D11: ='Historical Financial Statements'!D16 | E11: ='Historical Financial Statements'!E16 | F11: ='Historical Financial Statements'!F16 | G11: ='Historical Financial Statements'!G16 | H11: ='Historical Financial Statements'!H16 | I11: ='Assumptions'!I50*I6 | J11: ='Assumptions'!J50*J6 | K11: ='Assumptions'!K50*K6 | L11: ='Assumptions'!L50*L6 | M11: ='Assumptions'!M50*M6 | N11: ='Assumptions'!N50*N6 | O11: ='Assumptions'!O50*O6

Sheet Equity Schedule
A1: EQUITY SCHEDULE
A4: INR Crore | B4: FY2020 | C4: FY2021 | D4: FY2022 | E4: FY2023 | F4: FY2024 | G4: FY2025 | H4: FY2026 | I4: FY2027 | J4: FY2028 | K4: FY2029 | L4: FY2030 | M4: FY2031 | N4: FY2032 | O4: FY2033
A5: Other equity (reserves) roll-forward
A6: Opening other equity | I6: ='Forecast Financial Statements'!H29 | J6: =I10 | K6: =J10 | L6: =K10 | M6: =L10 | N6: =M10 | O6: =N10
A7: Add: profit after tax | I7: ='Forecast Financial Statements'!I20 | J7: ='Forecast Financial Statements'!J20 | K7: ='Forecast Financial Statements'!K20 | L7: ='Forecast Financial Statements'!L20 | M7: ='Forecast Financial Statements'!M20 | N7: ='Forecast Financial Statements'!N20 | O7: ='Forecast Financial Statements'!O20
A8: Less: dividends | I8: =-'Forecast Financial Statements'!I22 | J8: =-'Forecast Financial Statements'!J22 | K8: =-'Forecast Financial Statements'!K22 | L8: =-'Forecast Financial Statements'!L22 | M8: =-'Forecast Financial Statements'!M22 | N8: =-'Forecast Financial Statements'!N22 | O8: =-'Forecast Financial Statements'!O22
A9: Add: other comprehensive income | I9: 0 | J9: 0 | K9: 0 | L9: 0 | M9: 0 | N9: 0 | O9: 0
A10: Closing other equity | I10: =SUM(I6:I9) | J10: =SUM(J6:J9) | K10: =SUM(K6:K9) | L10: =SUM(L6:L9) | M10: =SUM(M6:M9) | N10: =SUM(N6:N9) | O10: =SUM(O6:O9)
A12: Equity share capital (constant) | I12: 696.41 | J12: 696.41 | K12: 696.41 | L12: 696.41 | M12: 696.41 | N12: 696.41 | O12: 696.41
A13: Total shareholders equity | I13: =I10+I12 | J13: =J10+J12 | K13: =K10+K12 | L13: =L10+L12 | M13: =M10+M12 | N13: =N10+N12 | O13: =O10+O12

Sheet Other Assets & Liabilities
A1: OTHER ASSETS & LIABILITIES
A4: INR Crore | B4: FY2020 | C4: FY2021 | D4: FY2022 | E4: FY2023 | F4: FY2024 | G4: FY2025 | H4: FY2026 | I4: FY2027 | J4: FY2028 | K4: FY2029 | L4: FY2030 | M4: FY2031 | N4: FY2032 | O4: FY2033
A5: Other (non-WC) assets & liabilities
A6: Capital work-in-progress | B6: ='Historical Financial Statements'!B29 | C6: ='Historical Financial Statements'!C29 | D6: ='Historical Financial Statements'!D29 | E6: ='Historical Financial Statements'!E29 | F6: ='Historical Financial Statements'!F29 | G6: ='Historical Financial Statements'!G29 | H6: ='Historical Financial Statements'!H29 | I6: ='Assumptions'!I44 | J6: ='Assumptions'!J44 | K6: ='Assumptions'!K44 | L6: ='Assumptions'!L44 | M6: ='Assumptions'!M44 | N6: ='Assumptions'!N44 | O6: ='Assumptions'!O44
A7: Investments | B7: ='Historical Financial Statements'!B30 | C7: ='Historical Financial Statements'!C30 | D7: ='Historical Financial Statements'!D30 | E7: ='Historical Financial Statements'!E30 | F7: ='Historical Financial Statements'!F30 | G7: ='Historical Financial Statements'!G30 | H7: ='Historical Financial Statements'!H30 | I7: ='Assumptions'!I45 | J7: ='Assumptions'!J45 | K7: ='Assumptions'!K45 | L7: ='Assumptions'!L45 | M7: ='Assumptions'!M45 | N7: ='Assumptions'!N45 | O7: ='Assumptions'!O45
A8: Contract assets - current (memo, from WC) | I8: ='Working Capital Schedule'!I11 | J8: ='Working Capital Schedule'!J11 | K8: ='Working Capital Schedule'!K11 | L8: ='Working Capital Schedule'!L11 | M8: ='Working Capital Schedule'!M11 | N8: ='Working Capital Schedule'!N11 | O8: ='Working Capital Schedule'!O11
A9: Other operating assets (memo, from WC) | I9: ='Working Capital Schedule'!I14 | J9: ='Working Capital Schedule'!J14 | K9: ='Working Capital Schedule'!K14 | L9: ='Working Capital Schedule'!L14 | M9: ='Working Capital Schedule'!M14 | N9: ='Working Capital Schedule'!N14 | O9: ='Working Capital Schedule'!O14
A10: Contract liabilities - current (memo, from WC) | I10: ='Working Capital Schedule'!I19 | J10: ='Working Capital Schedule'!J19 | K10: ='Working Capital Schedule'!K19 | L10: ='Working Capital Schedule'!L19 | M10: ='Working Capital Schedule'!M19 | N10: ='Working Capital Schedule'!N19 | O10: ='Working Capital Schedule'!O19
A11: Provisions & other liabilities (memo, from WC) | I11: ='Working Capital Schedule'!I23 | J11: ='Working Capital Schedule'!J23 | K11: ='Working Capital Schedule'!K23 | L11: ='Working Capital Schedule'!L23 | M11: ='Working Capital Schedule'!M23 | N11: ='Working Capital Schedule'!N23 | O11: ='Working Capital Schedule'!O23

Sheet Cash Flow Statement
A1: CASH FLOW STATEMENT
A2: Indirect method. FY20-26 reported; FY27-33 = PAT + D&A - increase in NWC; investing & financing from schedules. No plugs.
A4: INR Crore | B4: FY2020 | C4: FY2021 | D4: FY2022 | E4: FY2023 | F4: FY2024 | G4: FY2025 | H4: FY2026 | I4: FY2027 | J4: FY2028 | K4: FY2029 | L4: FY2030 | M4: FY2031 | N4: FY2032 | O4: FY2033
A5: A. Operating activities
A6: Profit after tax | I6: ='Forecast Financial Statements'!I20 | J6: ='Forecast Financial Statements'!J20 | K6: ='Forecast Financial Statements'!K20 | L6: ='Forecast Financial Statements'!L20 | M6: ='Forecast Financial Statements'!M20 | N6: ='Forecast Financial Statements'!N20 | O6: ='Forecast Financial Statements'!O20
A7: Add: depreciation & amortisation | I7: ='Depreciation Schedule'!I8 | J7: ='Depreciation Schedule'!J8 | K7: ='Depreciation Schedule'!K8 | L7: ='Depreciation Schedule'!L8 | M7: ='Depreciation Schedule'!M8 | N7: ='Depreciation Schedule'!N8 | O7: ='Depreciation Schedule'!O8
A8: (Increase)/decrease in working capital | I8: ='Working Capital Schedule'!I27 | J8: ='Working Capital Schedule'!J27 | K8: ='Working Capital Schedule'!K27 | L8: ='Working Capital Schedule'!L27 | M8: ='Working Capital Schedule'!M27 | N8: ='Working Capital Schedule'!N27 | O8: ='Working Capital Schedule'!O27
A9: Cash flow from operating activities | B9: ='Historical Financial Statements'!B42 | C9: ='Historical Financial Statements'!C42 | D9: ='Historical Financial Statements'!D42 | E9: ='Historical Financial Statements'!E42 | F9: ='Historical Financial Statements'!F42 | G9: ='Historical Financial Statements'!G42 | H9: ='Historical Financial Statements'!H42 | I9: =SUM(I6:I8) | J9: =SUM(J6:J8) | K9: =SUM(K6:K8) | L9: =SUM(L6:L8) | M9: =SUM(M6:M8) | N9: =SUM(N6:N8) | O9: =SUM(O6:O8)
A11: B. Investing activities
A12: Capital expenditure | I12: =-'Assumptions'!I35 | J12: =-'Assumptions'!J35 | K12: =-'Assumptions'!K35 | L12: =-'Assumptions'!L35 | M12: =-'Assumptions'!M35 | N12: =-'Assumptions'!N35 | O12: =-'Assumptions'!O35
A13: Change in CWIP | I13: =-('Assumptions'!I44-'Forecast Financial Statements'!H54) | J13: =-('Assumptions'!J44-'Assumptions'!I44) | K13: =-('Assumptions'!K44-'Assumptions'!J44) | L13: =-('Assumptions'!L44-'Assumptions'!K44) | M13: =-('Assumptions'!M44-'Assumptions'!L44) | N13: =-('Assumptions'!N44-'Assumptions'!M44) | O13: =-('Assumptions'!O44-'Assumptions'!N44)
A14: Change in investments | I14: =-('Assumptions'!I45-'Forecast Financial Statements'!H55) | J14: =-('Assumptions'!J45-'Assumptions'!I45) | K14: =-('Assumptions'!K45-'Assumptions'!J45) | L14: =-('Assumptions'!L45-'Assumptions'!K45) | M14: =-('Assumptions'!M45-'Assumptions'!L45) | N14: =-('Assumptions'!N45-'Assumptions'!M45) | O14: =-('Assumptions'!O45-'Assumptions'!N45)
A15: Cash flow from investing activities | B15: ='Historical Financial Statements'!B43 | C15: ='Historical Financial Statements'!C43 | D15: ='Historical Financial Statements'!D43 | E15: ='Historical Financial Statements'!E43 | F15: ='Historical Financial Statements'!F43 | G15: ='Historical Financial Statements'!G43 | H15: ='Historical Financial Statements'!H43 | I15: =SUM(I12:I14) | J15: =SUM(J12:J14) | K15: =SUM(K12:K14) | L15: =SUM(L12:L14) | M15: =SUM(M12:M14) | N15: =SUM(N12:N14) | O15: =SUM(O12:O14)
A17: C. Financing activities
A18: New borrowings | I18: ='Debt Schedule'!I7 | J18: ='Debt Schedule'!J7 | K18: ='Debt Schedule'!K7 | L18: ='Debt Schedule'!L7 | M18: ='Debt Schedule'!M7 | N18: ='Debt Schedule'!N7 | O18: ='Debt Schedule'!O7
A19: Debt repayment | I19: ='Debt Schedule'!I8 | J19: ='Debt Schedule'!J8 | K19: ='Debt Schedule'!K8 | L19: ='Debt Schedule'!L8 | M19: ='Debt Schedule'!M8 | N19: ='Debt Schedule'!N8 | O19: ='Debt Schedule'!O8
A20: Dividends paid | I20: =-'Forecast Financial Statements'!I22 | J20: =-'Forecast Financial Statements'!J22 | K20: =-'Forecast Financial Statements'!K22 | L20: =-'Forecast Financial Statements'!L22 | M20: =-'Forecast Financial Statements'!M22 | N20: =-'Forecast Financial Statements'!N22 | O20: =-'Forecast Financial Statements'!O22
A21: Cash flow from financing activities | B21: ='Historical Financial Statements'!B44 | C21: ='Historical Financial Statements'!C44 | D21: ='Historical Financial Statements'!D44 | E21: ='Historical Financial Statements'!E44 | F21: ='Historical Financial Statements'!F44 | G21: ='Historical Financial Statements'!G44 | H21: ='Historical Financial Statements'!H44 | I21: =SUM(I18:I20) | J21: =SUM(J18:J20) | K21: =SUM(K18:K20) | L21: =SUM(L18:L20) | M21: =SUM(M18:M20) | N21: =SUM(N18:N20) | O21: =SUM(O18:O20)
A23: Net increase/(decrease) in cash | B23: ='Historical Financial Statements'!B45 | C23: ='Historical Financial Statements'!C45 | D23: ='Historical Financial Statements'!D45 | E23: ='Historical Financial Statements'!E45 | F23: ='Historical Financial Statements'!F45 | G23: ='Historical Financial Statements'!G45 | H23: ='Historical Financial Statements'!H45 | I23: =I9+I15+I21 | J23: =J9+J15+J21 | K23: =K9+K15+K21 | L23: =L9+L15+L21 | M23: =M9+M15+M21 | N23: =N9+N15+N21 | O23: =O9+O15+O21
A24: Opening cash & bank | B24: 6353 | C24: 6961 | D24: 7084 | E24: 6297 | F24: 7126 | G24: 7400 | H24: 6004 | I24: ='Forecast Financial Statements'!H67 | J24: =I25 | K24: =J25 | L24: =K25 | M24: =L25 | N24: =M25 | O24: =N25
A25: Closing cash & bank | B25: 6961 | C25: 7084 | D25: 6297 | E25: 7126 | F25: 7400 | G25: 6004 | H25: 11866.62 | I25: =I24+I23 | J25: =J24+J23 | K25: =K24+K23 | L25: =L24+L23 | M25: =M24+M23 | N25: =N24+N23 | O25: =O24+O23
A26: FY20-26 operating/investing/financing shown at reported subtotal level; cash balances rolled from reported net cash flow (FY26 anchor estimated).

Sheet Forecast Financial Statements
A1: FORECAST FINANCIAL STATEMENTS
A2: Integrated three-statement model. FY20-26 reported; FY27-33 forecast (linked to schedules). BS detail shown FY26 onward.
A3: A. INCOME STATEMENT
A4: Particulars | B4: FY2020 | C4: FY2021 | D4: FY2022 | E4: FY2023 | F4: FY2024 | G4: FY2025 | H4: FY2026 | I4: FY2027 | J4: FY2028 | K4: FY2029 | L4: FY2030 | M4: FY2031 | N4: FY2032 | O4: FY2033
A5: Sales | B5: ='Historical Financial Statements'!B5 | C5: ='Historical Financial Statements'!C5 | D5: ='Historical Financial Statements'!D5 | E5: ='Historical Financial Statements'!E5 | F5: ='Historical Financial Statements'!F5 | G5: ='Historical Financial Statements'!G5 | H5: ='Historical Financial Statements'!H5 | I5: ='Revenue Build-up'!I15 | J5: ='Revenue Build-up'!J15 | K5: ='Revenue Build-up'!K15 | L5: ='Revenue Build-up'!L15 | M5: ='Revenue Build-up'!M15 | N5: ='Revenue Build-up'!N15 | O5: ='Revenue Build-up'!O15
A6: Total COGS | B6: ='Historical Financial Statements'!B6 | C6: ='Historical Financial Statements'!C6 | D6: ='Historical Financial Statements'!D6 | E6: ='Historical Financial Statements'!E6 | F6: ='Historical Financial Statements'!F6 | G6: ='Historical Financial Statements'!G6 | H6: ='Historical Financial Statements'!H6 | I6: ='Cost Forecast'!I13 | J6: ='Cost Forecast'!J13 | K6: ='Cost Forecast'!K13 | L6: ='Cost Forecast'!L13 | M6: ='Cost Forecast'!M13 | N6: ='Cost Forecast'!N13 | O6: ='Cost Forecast'!O13
A7: Gross Profit | B7: =B5-B6 | C7: =C5-C6 | D7: =D5-D6 | E7: =E5-E6 | F7: =F5-F6 | G7: =G5-G6 | H7: =H5-H6 | I7: =I5-I6 | ... O7: =O5-O6
A8: Operating Expenses
A9: Employee Cost | B9: ='Historical Financial Statements'!B9 | C9: ='Historical Financial Statements'!C9 | D9: ='Historical Financial Statements'!D9 | E9: ='Historical Financial Statements'!E9 | F9: ='Historical Financial Statements'!F9 | G9: ='Historical Financial Statements'!G9 | H9: ='Historical Financial Statements'!H9 | I9: ='Cost Forecast'!I16 | J9: ='Cost Forecast'!J16 | K9: ='Cost Forecast'!K16 | L9: ='Cost Forecast'!L16 | M9: ='Cost Forecast'!M16 | N9: ='Cost Forecast'!N16 | O9: ='Cost Forecast'!O16
A10: Selling and admin | B10: ='Historical Financial Statements'!B10 | C10: ='Historical Financial Statements'!C10 | D10: ='Historical Financial Statements'!D10 | E10: ='Historical Financial Statements'!E10 | F10: ='Historical Financial Statements'!F10 | G10: ='Historical Financial Statements'!G10 | H10: ='Historical Financial Statements'!H10 | I10: ='Cost Forecast'!I20 | J10: ='Cost Forecast'!J20 | K10: ='Cost Forecast'!K20 | L10: ='Cost Forecast'!L20 | M10: ='Cost Forecast'!M20 | N10: ='Cost Forecast'!N20 | O10: ='Cost Forecast'!O20
A11: Total Operating Expenses | B11: =B9+B10 | C11: =C9+C10 | D11: =D9+D10 | E11: =E9+E10 | F11: =F9+F10 | G11: =G9+G10 | H11: =H9+H10 | I11: =I9+I10 | ... O11: =O9+O10
A12: EBITDA | B12: =B7-B11 | C12: =C7-C11 | D12: =D7-D11 | E12: =E7-E11 | F12: =F7-F11 | G12: =G7-G11 | H12: =H7-H11 | I12: =I7-I11 | ... O12: =O7-O11
A13: Depreciation & Amortization | B13: ='Historical Financial Statements'!B13 | C13: ='Historical Financial Statements'!C13 | D13: ='Historical Financial Statements'!D13 | E13: ='Historical Financial Statements'!E13 | F13: ='Historical Financial Statements'!F13 | G13: ='Historical Financial Statements'!G13 | H13: ='Historical Financial Statements'!H13 | I13: ='Depreciation Schedule'!I8 | J13: ='Depreciation Schedule'!J8 | K13: ='Depreciation Schedule'!K8 | L13: ='Depreciation Schedule'!L8 | M13: ='Depreciation Schedule'!M8 | N13: ='Depreciation Schedule'!N8 | O13: ='Depreciation Schedule'!O8
A14: EBIT | B14: =B12-B13 | C14: =C12-C13 | D14: =D12-D13 | E14: =E12-E13 | F14: =F12-F13 | G14: =G12-G13 | H14: =H12-H13 | I14: =I12-I13 | ... O14: =O12-O13
A15: Other Income | B15: ='Historical Financial Statements'!B15 | C15: ='Historical Financial Statements'!C15 | D15: ='Historical Financial Statements'!D15 | E15: ='Historical Financial Statements'!E15 | F15: ='Historical Financial Statements'!F15 | G15: ='Historical Financial Statements'!G15 | H15: ='Historical Financial Statements'!H15 | I15: ='Assumptions'!I23*I5 | J15: ='Assumptions'!J23*J5 | K15: ='Assumptions'!K23*K5 | L15: ='Assumptions'!L23*L5 | M15: ='Assumptions'!M23*M5 | N15: ='Assumptions'!N23*N5 | O15: ='Assumptions'!O23*O5
A16: Interest Paid | B16: ='Historical Financial Statements'!B16 | C16: ='Historical Financial Statements'!C16 | D16: ='Historical Financial Statements'!D16 | E16: ='Historical Financial Statements'!E16 | F16: ='Historical Financial Statements'!F16 | G16: ='Historical Financial Statements'!G16 | H16: ='Historical Financial Statements'!H16 | I16: ='Debt Schedule'!I11 | J16: ='Debt Schedule'!J11 | K16: ='Debt Schedule'!K11 | L16: ='Debt Schedule'!L11 | M16: ='Debt Schedule'!M11 | N16: ='Debt Schedule'!N11 | O16: ='Debt Schedule'!O11
A17: Profit Before Tax (PBT) | B17: =B14+B15-B16 | C17: =C14+C15-C16 | D17: =D14+D15-D16 | E17: =E14+E15-E16 | F17: =F14+F15-F16 | G17: =G14+G15-G16 | H17: =H14+H15-H16 | I17: =I14+I15-I16 | ... O17: =O14+O15-O16
A18: Tax | B18: ='Historical Financial Statements'!B18 | C18: ='Historical Financial Statements'!C18 | D18: ='Historical Financial Statements'!D18 | E18: ='Historical Financial Statements'!E18 | F18: ='Historical Financial Statements'!F18 | G18: ='Historical Financial Statements'!G18 | H18: ='Historical Financial Statements'!H18 | I18: ='Assumptions'!I46*I17 | J18: ='Assumptions'!J46*J17 | K18: ='Assumptions'!K46*K17 | L18: ='Assumptions'!L46*L17 | M18: ='Assumptions'!M46*M17 | N18: ='Assumptions'!N46*N17 | O18: ='Assumptions'!O46*O17
A19: Adjustments | B19: ='Historical Financial Statements'!B19 | C19: ='Historical Financial Statements'!C19 | D19: ='Historical Financial Statements'!D19 | E19: ='Historical Financial Statements'!E19 | F19: ='Historical Financial Statements'!F19 | G19: ='Historical Financial Statements'!G19 | H19: ='Historical Financial Statements'!H19 | I19: 0 | J19: 0 | K19: 0 | L19: 0 | M19: 0 | N19: 0 | O19: 0
A20: Profit After Tax (PAT) | B20: =B17-B18+B19 | C20: =C17-C18+C19 | D20: =D17-D18+D19 | E20: =E17-E18+E19 | F20: =F17-F18+F19 | G20: =G17-G18+G19 | H20: =H17-H18+H19 | I20: =I17-I18+I19 | ... O20: =O17-O18+O19
A21: EPS (INR) | B21: =B20/'Assumptions'!C66 | C21: =C20/'Assumptions'!C66 | D21: =D20/'Assumptions'!C66 | E21: =E20/'Assumptions'!C66 | F21: =F20/'Assumptions'!C66 | G21: =G20/'Assumptions'!C66 | H21: =H20/'Assumptions'!C66 | I21: =I20/'Assumptions'!C66 | J21: =J20/'Assumptions'!C66 | K21: =K20/'Assumptions'!C66 | L21: =L20/'Assumptions'!C66 | M21: =M20/'Assumptions'!C66 | N21: =N20/'Assumptions'!C66 | O21: =O20/'Assumptions'!C66
A22: Dividend | B22: ='Historical Financial Statements'!B22 | C22: ='Historical Financial Statements'!C22 | D22: ='Historical Financial Statements'!D22 | E22: ='Historical Financial Statements'!E22 | F22: ='Historical Financial Statements'!F22 | G22: ='Historical Financial Statements'!G22 | H22: ='Historical Financial Statements'!H22 | I22: ='Assumptions'!I47*I20 | J22: ='Assumptions'!J47*J20 | K22: ='Assumptions'!K47*K20 | L22: ='Assumptions'!L47*L20 | M22: ='Assumptions'!M47*M20 | N22: ='Assumptions'!N47*N20 | O22: ='Assumptions'!O47*O20
A24: B. BALANCE SHEET (FY2020-26 reported; FY2027-33 forecast) - current vs non-current
A25: Particulars | B25: FY2020 | C25: FY2021 | D25: FY2022 | E25: FY2023 | F25: FY2024 | G25: FY2025 | H25: FY2026 | I25: FY2027 | J25: FY2028 | K25: FY2029 | L25: FY2030 | M25: FY2031 | N25: FY2032 | O25: FY2033
A26: EQUITY & LIABILITIES
A27: Shareholders' Fund
A28: Share Capital | B28: 696.41 | C28: 696.41 | D28: 696.41 | E28: 696.41 | F28: 696.41 | G28: 696.41 | H28: 696.41 | I28: ='Equity Schedule'!I12 | J28: ='Equity Schedule'!J12 | K28: ='Equity Schedule'!K12 | L28: ='Equity Schedule'!L12 | M28: ='Equity Schedule'!M12 | N28: ='Equity Schedule'!N12 | O28: ='Equity Schedule'!O12
A29: Reserve & Surplus | B29: 27964.31 | C29: 25287.25 | D29: 25810.19 | E29: 23681.85 | F29: 23742.24 | G29: 24025.75 | H29: 25450.19 | I29: ='Equity Schedule'!I10 | J29: ='Equity Schedule'!J10 | K29: ='Equity Schedule'!K10 | L29: ='Equity Schedule'!L10 | M29: ='Equity Schedule'!M10 | N29: ='Equity Schedule'!N10 | O29: ='Equity Schedule'!O10
A30: Total Shareholders' Fund | B30: =B28+B29 | C30: =C28+C29 | D30: =D28+D29 | E30: =E28+E29 | F30: =F28+F29 | G30: =G28+G29 | H30: =H28+H29 | I30: =I28+I29 | ... O30: =O28+O29
A32: Non-Current Liabilities
A33: Long-term Borrowings | B33: 0 | C33: 0 | D33: 0 | E33: 0 | F33: 0 | G33: 0 | H33: 168.18 | I33: ='Assumptions'!I51*'Debt Schedule'!I9 | J33: ='Assumptions'!J51*'Debt Schedule'!J9 | K33: ='Assumptions'!K51*'Debt Schedule'!K9 | L33: ='Assumptions'!L51*'Debt Schedule'!L9 | M33: ='Assumptions'!M51*'Debt Schedule'!M9 | N33: ='Assumptions'!N51*'Debt Schedule'!N9 | O33: ='Assumptions'!O51*'Debt Schedule'!O9
A34: Trade Payables - non-current | B34: 376.46 | C34: 439.99 | D34: 405.73 | E34: 449.4 | F34: 595.6 | G34: 1108.19 | H34: 1343.44 | I34: ='Working Capital Schedule'!I18 | J34: ='Working Capital Schedule'!J18 | K34: ='Working Capital Schedule'!K18 | L34: ='Working Capital Schedule'!L18 | M34: ='Working Capital Schedule'!M18 | N34: ='Working Capital Schedule'!N18 | O34: ='Working Capital Schedule'!O18
A35: Contract Liabilities - non-current | B35: 3758.65 | C35: 4392.97 | D35: 4050.94 | E35: 4486.9 | F35: 5946.6 | G35: 11064.42 | H35: 13413.24 | I35: ='Working Capital Schedule'!I20 | J35: ='Working Capital Schedule'!J20 | K35: ='Working Capital Schedule'!K20 | L35: ='Working Capital Schedule'!L20 | M35: ='Working Capital Schedule'!M20 | N35: ='Working Capital Schedule'!N20 | O35: ='Working Capital Schedule'!O20
A36: Long-term Provisions | B36: 4225.16 | C36: 3925.56 | D36: 3771.21 | E36: 4101.02 | F36: 2489.08 | G36: 2585.56 | H36: 2354.62 | I36: ='Working Capital Schedule'!I22 | J36: ='Working Capital Schedule'!J22 | K36: ='Working Capital Schedule'!K22 | L36: ='Working Capital Schedule'!L22 | M36: ='Working Capital Schedule'!M22 | N36: ='Working Capital Schedule'!N22 | O36: ='Working Capital Schedule'!O22
A37: Other Non-Current Liabilities | B37: 128.16 | C37: 149.79 | D37: 138.13 | E37: 152.99 | F37: 202.76 | G37: 377.26 | H37: 457.35 | I37: ='Working Capital Schedule'!I24 | J37: ='Working Capital Schedule'!J24 | K37: ='Working Capital Schedule'!K24 | L37: ='Working Capital Schedule'!L24 | M37: ='Working Capital Schedule'!M24 | N37: ='Working Capital Schedule'!N24 | O37: ='Working Capital Schedule'!O24
A38: Total Non-Current Liabilities | B38: =SUM(B33:B37) | C38: =SUM(C33:C37) | D38: =SUM(D33:D37) | E38: =SUM(E33:E37) | F38: =SUM(F33:F37) | G38: =SUM(G33:G37) | H38: =SUM(H33:H37) | I38: =SUM(I33:I37) | ... O38: =SUM(O33:O37)
A40: Current Liabilities
A41: Short-term Borrowings | B41: 4947.92 | C41: 4849.28 | D41: 4745 | E41: 5385 | F41: 8808 | G41: 8795 | H41: 8018.77 | I41: ='Debt Schedule'!I9-I33 | J41: ='Debt Schedule'!J9-J33 | K41: ='Debt Schedule'!K9-K33 | L41: ='Debt Schedule'!L9-L33 | M41: ='Debt Schedule'!M9-M33 | N41: ='Debt Schedule'!N9-N33 | O41: ='Debt Schedule'!O9-O33
A42: Trade Payables - current | B42: 8829.16 | C42: 6683.51 | D42: 7749.59 | E42: 9895.83 | F42: 8696.24 | G42: 9540.92 | H42: 10491.6 | I42: ='Working Capital Schedule'!I17 | J42: ='Working Capital Schedule'!J17 | K42: ='Working Capital Schedule'!K17 | L42: ='Working Capital Schedule'!L17 | M42: ='Working Capital Schedule'!M17 | N42: ='Working Capital Schedule'!N17 | O42: ='Working Capital Schedule'!O17
A43: Contract Liabilities - current | B43: 5833.72 | C43: 5830.88 | D43: 5863.55 | E43: 5331.17 | F43: 5171.28 | G43: 6532.77 | H43: 9110.39 | I43: ='Working Capital Schedule'!I19 | J43: ='Working Capital Schedule'!J19 | K43: ='Working Capital Schedule'!K19 | L43: ='Working Capital Schedule'!L19 | M43: ='Working Capital Schedule'!M19 | N43: ='Working Capital Schedule'!N19 | O43: ='Working Capital Schedule'!O19
A44: Provisions - current | B44: 1228.75 | C44: 1228.15 | D44: 1235.03 | E44: 1122.9 | F44: 1089.22 | G44: 1375.99 | H44: 1918.91 | I44: ='Working Capital Schedule'!I21 | J44: ='Working Capital Schedule'!J21 | K44: ='Working Capital Schedule'!K21 | L44: ='Working Capital Schedule'!L21 | M44: ='Working Capital Schedule'!M21 | N44: ='Working Capital Schedule'!N21 | O44: ='Working Capital Schedule'!O21
A45: Other Current Liabilities | B45: 1768.93 | C45: 1768.08 | D45: 1777.98 | E45: 1616.55 | F45: 1568.07 | G45: 1980.91 | H45: 2762.51 | I45: ='Working Capital Schedule'!I23 | J45: ='Working Capital Schedule'!J23 | K45: ='Working Capital Schedule'!K23 | L45: ='Working Capital Schedule'!L23 | M45: ='Working Capital Schedule'!M23 | N45: ='Working Capital Schedule'!N23 | O45: ='Working Capital Schedule'!O23
A46: Total Current Liabilities | B46: =SUM(B41:B45) | C46: =SUM(C41:C45) | D46: =SUM(D41:D45) | E46: =SUM(E41:E45) | F46: =SUM(F41:F45) | G46: =SUM(G41:G45) | H46: =SUM(H41:H45) | I46: =SUM(I41:I45) | ... O46: =SUM(O41:O45)
A47: Total Liabilities | B47: =B38+B46 | C47: =C38+C46 | D47: =D38+D46 | E47: =E38+E46 | F47: =F38+F46 | G47: =G38+G46 | H47: =H38+H46 | I47: =I38+I46 | ... O47: =O38+O46
A49: TOTAL EQUITY & LIABILITIES | B49: =B30+B47 | C49: =C30+C47 | D49: =D30+D47 | E49: =E30+E47 | F49: =F30+F47 | G49: =G30+G47 | H49: =H30+H47 | I49: =I30+I47 | ... O49: =O30+O47
A51: ASSETS
A52: Non-Current Assets
A53: Property, Plant & Equipment (incl. intangibles) | B53: 2817 | C53: 2491 | D53: 2398 | E53: 2476 | F53: 2574 | G53: 2947 | H53: 3094.38 | I53: ='Fixed Asset Schedule'!I10 | J53: ='Fixed Asset Schedule'!J10 | K53: ='Fixed Asset Schedule'!K10 | L53: ='Fixed Asset Schedule'!L10 | M53: ='Fixed Asset Schedule'!M10 | N53: ='Fixed Asset Schedule'!N10 | O53: ='Fixed Asset Schedule'!O10
A54: Capital Work in Progress | B54: 314 | C54: 420 | D54: 431 | E54: 354 | F54: 308 | G54: 195 | H54: 399.2 | I54: ='Assumptions'!I44 | J54: ='Assumptions'!J44 | K54: ='Assumptions'!K44 | L54: ='Assumptions'!L44 | M54: ='Assumptions'!M44 | N54: ='Assumptions'!N44 | O54: ='Assumptions'!O44
A55: Investments | B55: 162 | C55: 185 | D55: 205 | E55: 235 | F55: 256 | G55: 276 | H55: 302.06 | I55: ='Assumptions'!I45 | J55: ='Assumptions'!J45 | K55: ='Assumptions'!K45 | L55: ='Assumptions'!L45 | M55: ='Assumptions'!M45 | N55: ='Assumptions'!N45 | O55: ='Assumptions'!O45
A56: Trade Receivables - non-current | B56: 2751.82 | C56: 2757.31 | D56: 2937.54 | E56: 2754.88 | F56: 2468.8 | G56: 2535.56 | H56: 2426.93 | I56: ='Working Capital Schedule'!I9 | J56: ='Working Capital Schedule'!J9 | K56: ='Working Capital Schedule'!K9 | L56: ='Working Capital Schedule'!L9 | M56: ='Working Capital Schedule'!M9 | N56: ='Working Capital Schedule'!N9 | O56: ='Working Capital Schedule'!O9
A57: Contract Assets - non-current | B57: 16097.22 | C57: 16129.35 | D57: 17183.61 | E57: 16115.1 | F57: 14441.63 | G57: 14832.18 | H57: 14196.72 | I57: ='Working Capital Schedule'!I12 | J57: ='Working Capital Schedule'!J12 | K57: ='Working Capital Schedule'!K12 | L57: ='Working Capital Schedule'!L12 | M57: ='Working Capital Schedule'!M12 | N57: ='Working Capital Schedule'!N12 | O57: ='Working Capital Schedule'!O12
A58: Deferred Tax Assets | B58: 4005.73 | C58: 4013.73 | D58: 4276.08 | E58: 4010.18 | F58: 3593.75 | G58: 3690.93 | H58: 3532.8 | I58: ='Working Capital Schedule'!I13 | J58: ='Working Capital Schedule'!J13 | K58: ='Working Capital Schedule'!K13 | L58: ='Working Capital Schedule'!L13 | M58: ='Working Capital Schedule'!M13 | N58: ='Working Capital Schedule'!N13 | O58: ='Working Capital Schedule'!O13
A59: Other Non-Current Assets | B59: 882.35 | C59: 884.11 | D59: 941.89 | E59: 883.32 | F59: 791.59 | G59: 813.01 | H59: 778.17 | I59: ='Working Capital Schedule'!I15 | J59: ='Working Capital Schedule'!J15 | K59: ='Working Capital Schedule'!K15 | L59: ='Working Capital Schedule'!L15 | M59: ='Working Capital Schedule'!M15 | N59: ='Working Capital Schedule'!N15 | O59: ='Working Capital Schedule'!O15
A60: Total Non-Current Assets | B60: =SUM(B53:B59) | C60: =SUM(C53:C59) | D60: =SUM(D53:D59) | E60: =SUM(E53:E59) | F60: =SUM(F53:F59) | G60: =SUM(G53:G59) | H60: =SUM(H53:H59) | I60: =SUM(I53:I59) | ... O60: =SUM(O53:O59)
A62: Current Assets
A63: Trade Receivables - current | B63: 7108.6 | C63: 4035.07 | D63: 3024.75 | E63: 3128.35 | F63: 4785.38 | G63: 5884.35 | H63: 6796.27 | I63: ='Working Capital Schedule'!I8 | J63: ='Working Capital Schedule'!J8 | K63: ='Working Capital Schedule'!K8 | L63: ='Working Capital Schedule'!L8 | M63: ='Working Capital Schedule'!M8 | N63: ='Working Capital Schedule'!N8 | O63: ='Working Capital Schedule'!O8
A64: Inventories | B64: 8908.23 | C64: 7194.45 | D64: 6560.21 | E64: 6755.9 | F64: 7220.57 | G64: 9869.49 | H64: 13334.58 | I64: ='Working Capital Schedule'!I10 | J64: ='Working Capital Schedule'!J10 | K64: ='Working Capital Schedule'!K10 | L64: ='Working Capital Schedule'!L10 | M64: ='Working Capital Schedule'!M10 | N64: ='Working Capital Schedule'!N10 | O64: ='Working Capital Schedule'!O10
A65: Contract Assets - current | B65: 8036.16 | C65: 8151.96 | D65: 8691.96 | E65: 10591.45 | F65: 12811.76 | G65: 15168.97 | H65: 15192.89 | I65: ='Working Capital Schedule'!I11 | J65: ='Working Capital Schedule'!J11 | K65: ='Working Capital Schedule'!K11 | L65: ='Working Capital Schedule'!L11 | M65: ='Working Capital Schedule'!M11 | N65: ='Working Capital Schedule'!N11 | O65: ='Working Capital Schedule'!O11
A66: Other Current Assets | B66: 2255.93 | C66: 2288.44 | D66: 2440.03 | E66: 2973.26 | F66: 3596.55 | G66: 4258.28 | H66: 4264.99 | I66: ='Working Capital Schedule'!I14 | J66: ='Working Capital Schedule'!J14 | K66: ='Working Capital Schedule'!K14 | L66: ='Working Capital Schedule'!L14 | M66: ='Working Capital Schedule'!M14 | N66: ='Working Capital Schedule'!N14 | O66: ='Working Capital Schedule'!O14
A67: Cash & Bank Balances | B67: 6418.59 | C67: 6701.45 | D67: 7153.69 | E67: 6642.58 | F67: 6157.47 | G67: 7612.41 | H67: 11866.62 | I67: ='Cash Flow Statement'!I25 | J67: ='Cash Flow Statement'!J25 | K67: ='Cash Flow Statement'!K25 | L67: ='Cash Flow Statement'!L25 | M67: ='Cash Flow Statement'!M25 | N67: ='Cash Flow Statement'!N25 | O67: ='Cash Flow Statement'!O25
A68: Total Current Assets | B68: =SUM(B63:B67) | C68: =SUM(C63:C67) | D68: =SUM(D63:D67) | E68: =SUM(E63:E67) | F68: =SUM(F63:F67) | G68: =SUM(G63:G67) | H68: =SUM(H63:H67) | I68: =SUM(I63:I67) | ... O68: =SUM(O63:O67)
A70: TOTAL ASSETS | B70: =B60+B68 | C70: =C60+C68 | D70: =D60+D68 | E70: =E60+E68 | F70: =F60+F68 | G70: =G60+G68 | H70: =H60+H68 | I70: =I60+I68 | ... O70: =O60+O68
A71: Balance check (TA - TE&L) | B71: =B70-B49 | C71: =C70-C49 | D71: =D70-D49 | E71: =E70-E49 | F71: =F70-F49 | G71: =G70-G49 | H71: =H70-H49 | I71: =I70-I49 | ... O71: =O70-O49
A72: Memo: total borrowings (LT+ST) | B72: =B33+B41 | C72: =C33+C41 | D72: =D33+D41 | E72: =E33+E41 | F72: =F33+F41 | G72: =G33+G41 | H72: =H33+H41 | I72: =I33+I41 | ... O72: =O33+O41
A73: Note: FY2026 current/non-current line items are audited actuals (annual-report / BSE Integrated Filing). FY2020-25 splits of contract assets & liabilities, non-current trade receivables, current provisions and deferred tax (orange) are derived by applying the FY2026 audited composition to each year's reported aggregate; reported section totals remain audited and the balance sheet ties every year.

Sheet Ratio Analysis
A1: RATIO ANALYSIS
A2: FY20-25 from Historical Financial Statements; FY26-33 from integrated Forecast statements.
A4: INR Crore | B4: FY2020 | C4: FY2021 | D4: FY2022 | E4: FY2023 | F4: FY2024 | G4: FY2025 | H4: FY2026 | I4: FY2027 | J4: FY2028 | K4: FY2029 | L4: FY2030 | M4: FY2031 | N4: FY2032 | O4: FY2033
A5: Growth & margins
A6: Revenue growth % | C6: ='Historical Financial Statements'!C5/'Historical Financial Statements'!B5-1 | D6: ='Historical Financial Statements'!D5/'Historical Financial Statements'!C5-1 | E6: ='Historical Financial Statements'!E5/'Historical Financial Statements'!D5-1 | F6: ='Historical Financial Statements'!F5/'Historical Financial Statements'!E5-1 | G6: ='Historical Financial Statements'!G5/'Historical Financial Statements'!F5-1 | H6: ='Forecast Financial Statements'!H5/'Historical Financial Statements'!G5-1 | I6: ='Forecast Financial Statements'!I5/'Forecast Financial Statements'!H5-1 | J6: ='Forecast Financial Statements'!J5/'Forecast Financial Statements'!I5-1 | K6: ='Forecast Financial Statements'!K5/'Forecast Financial Statements'!J5-1 | L6: ='Forecast Financial Statements'!L5/'Forecast Financial Statements'!K5-1 | M6: ='Forecast Financial Statements'!M5/'Forecast Financial Statements'!L5-1 | N6: ='Forecast Financial Statements'!N5/'Forecast Financial Statements'!M5-1 | O6: ='Forecast Financial Statements'!O5/'Forecast Financial Statements'!N5-1
A7: Gross margin % | B7: ='Historical Financial Statements'!B7/'Historical Financial Statements'!B5 | C7: ='Historical Financial Statements'!C7/'Historical Financial Statements'!C5 | D7: ='Historical Financial Statements'!D7/'Historical Financial Statements'!D5 | E7: ='Historical Financial Statements'!E7/'Historical Financial Statements'!E5 | F7: ='Historical Financial Statements'!F7/'Historical Financial Statements'!F5 | G7: ='Historical Financial Statements'!G7/'Historical Financial Statements'!G5 | H7: ='Forecast Financial Statements'!H7/'Forecast Financial Statements'!H5 | I7: ='Forecast Financial Statements'!I7/'Forecast Financial Statements'!I5 | J7: ='Forecast Financial Statements'!J7/'Forecast Financial Statements'!J5 | K7: ='Forecast Financial Statements'!K7/'Forecast Financial Statements'!K5 | L7: ='Forecast Financial Statements'!L7/'Forecast Financial Statements'!L5 | M7: ='Forecast Financial Statements'!M7/'Forecast Financial Statements'!M5 | N7: ='Forecast Financial Statements'!N7/'Forecast Financial Statements'!N5 | O7: ='Forecast Financial Statements'!O7/'Forecast Financial Statements'!O5
A8: EBITDA margin % | B8: ='Historical Financial Statements'!B12/'Historical Financial Statements'!B5 | C8: ='Historical Financial Statements'!C12/'Historical Financial Statements'!C5 | D8: ='Historical Financial Statements'!D12/'Historical Financial Statements'!D5 | E8: ='Historical Financial Statements'!E12/'Historical Financial Statements'!E5 | F8: ='Historical Financial Statements'!F12/'Historical Financial Statements'!F5 | G8: ='Historical Financial Statements'!G12/'Historical Financial Statements'!G5 | H8: ='Forecast Financial Statements'!H12/'Forecast Financial Statements'!H5 | I8: ='Forecast Financial Statements'!I12/'Forecast Financial Statements'!I5 | J8: ='Forecast Financial Statements'!J12/'Forecast Financial Statements'!J5 | K8: ='Forecast Financial Statements'!K12/'Forecast Financial Statements'!K5 | L8: ='Forecast Financial Statements'!L12/'Forecast Financial Statements'!L5 | M8: ='Forecast Financial Statements'!M12/'Forecast Financial Statements'!M5 | N8: ='Forecast Financial Statements'!N12/'Forecast Financial Statements'!N5 | O8: ='Forecast Financial Statements'!O12/'Forecast Financial Statements'!O5
A9: EBIT margin % | B9: ='Historical Financial Statements'!B14/'Historical Financial Statements'!B5 | C9: ='Historical Financial Statements'!C14/'Historical Financial Statements'!C5 | D9: ='Historical Financial Statements'!D14/'Historical Financial Statements'!D5 | E9: ='Historical Financial Statements'!E14/'Historical Financial Statements'!E5 | F9: ='Historical Financial Statements'!F14/'Historical Financial Statements'!F5 | G9: ='Historical Financial Statements'!G14/'Historical Financial Statements'!G5 | H9: ='Forecast Financial Statements'!H14/'Forecast Financial Statements'!H5 | I9: ='Forecast Financial Statements'!I14/'Forecast Financial Statements'!I5 | J9: ='Forecast Financial Statements'!J14/'Forecast Financial Statements'!J5 | K9: ='Forecast Financial Statements'!K14/'Forecast Financial Statements'!K5 | L9: ='Forecast Financial Statements'!L14/'Forecast Financial Statements'!L5 | M9: ='Forecast Financial Statements'!M14/'Forecast Financial Statements'!M5 | N9: ='Forecast Financial Statements'!N14/'Forecast Financial Statements'!N5 | O9: ='Forecast Financial Statements'!O14/'Forecast Financial Statements'!O5
A10: PAT margin % | B10: ='Historical Financial Statements'!B20/'Historical Financial Statements'!B5 | C10: ='Historical Financial Statements'!C20/'Historical Financial Statements'!C5 | D10: ='Historical Financial Statements'!D20/'Historical Financial Statements'!D5 | E10: ='Historical Financial Statements'!E20/'Historical Financial Statements'!E5 | F10: ='Historical Financial Statements'!F20/'Historical Financial Statements'!F5 | G10: ='Historical Financial Statements'!G20/'Historical Financial Statements'!G5 | H10: ='Forecast Financial Statements'!H20/'Forecast Financial Statements'!H5 | I10: ='Forecast Financial Statements'!I20/'Forecast Financial Statements'!I5 | J10: ='Forecast Financial Statements'!J20/'Forecast Financial Statements'!J5 | K10: ='Forecast Financial Statements'!K20/'Forecast Financial Statements'!K5 | L10: ='Forecast Financial Statements'!L20/'Forecast Financial Statements'!L5 | M10: ='Forecast Financial Statements'!M20/'Forecast Financial Statements'!M5 | N10: ='Forecast Financial Statements'!N20/'Forecast Financial Statements'!N5 | O10: ='Forecast Financial Statements'!O20/'Forecast Financial Statements'!O5
A12: Returns
A13: ROE % | C13: ='Historical Financial Statements'!C20/((('Historical Financial Statements'!C33+'Historical Financial Statements'!C34)+('Historical Financial Statements'!B33+'Historical Financial Statements'!B34))/2) | D13: ='Historical Financial Statements'!D20/((('Historical Financial Statements'!D33+'Historical Financial Statements'!D34)+('Historical Financial Statements'!C33+'Historical Financial Statements'!C34))/2) | E13: ='Historical Financial Statements'!E20/((('Historical Financial Statements'!E33+'Historical Financial Statements'!E34)+('Historical Financial Statements'!D33+'Historical Financial Statements'!D34))/2) | F13: ='Historical Financial Statements'!F20/((('Historical Financial Statements'!F33+'Historical Financial Statements'!F34)+('Historical Financial Statements'!E33+'Historical Financial Statements'!E34))/2) | G13: ='Historical Financial Statements'!G20/((('Historical Financial Statements'!G33+'Historical Financial Statements'!G34)+('Historical Financial Statements'!F33+'Historical Financial Statements'!F34))/2) | H13: ='Forecast Financial Statements'!H20/((('Forecast Financial Statements'!H28+'Forecast Financial Statements'!H29)+('Historical Financial Statements'!G33+'Historical Financial Statements'!G34))/2) | I13: ='Forecast Financial Statements'!I20/((('Forecast Financial Statements'!I28+'Forecast Financial Statements'!I29)+('Forecast Financial Statements'!H28+'Forecast Financial Statements'!H29))/2) | J13: ='Forecast Financial Statements'!J20/((('Forecast Financial Statements'!J28+'Forecast Financial Statements'!J29)+('Forecast Financial Statements'!I28+'Forecast Financial Statements'!I29))/2) | K13: ='Forecast Financial Statements'!K20/((('Forecast Financial Statements'!K28+'Forecast Financial Statements'!K29)+('Forecast Financial Statements'!J28+'Forecast Financial Statements'!J29))/2) | L13: ='Forecast Financial Statements'!L20/((('Forecast Financial Statements'!L28+'Forecast Financial Statements'!L29)+('Forecast Financial Statements'!K28+'Forecast Financial Statements'!K29))/2) | M13: ='Forecast Financial Statements'!M20/((('Forecast Financial Statements'!M28+'Forecast Financial Statements'!M29)+('Forecast Financial Statements'!L28+'Forecast Financial Statements'!L29))/2) | N13: ='Forecast Financial Statements'!N20/((('Forecast Financial Statements'!N28+'Forecast Financial Statements'!N29)+('Forecast Financial Statements'!M28+'Forecast Financial Statements'!M29))/2) | O13: ='Forecast Financial Statements'!O20/((('Forecast Financial Statements'!O28+'Forecast Financial Statements'!O29)+('Forecast Financial Statements'!N28+'Forecast Financial Statements'!N29))/2)
A14: ROCE % | B14: ='Historical Financial Statements'!B14/(('Historical Financial Statements'!B33+'Historical Financial Statements'!B34)+'Historical Financial Statements'!B35) | C14: ='Historical Financial Statements'!C14/(('Historical Financial Statements'!C33+'Historical Financial Statements'!C34)+'Historical Financial Statements'!C35) | D14: ='Historical Financial Statements'!D14/(('Historical Financial Statements'!D33+'Historical Financial Statements'!D34)+'Historical Financial Statements'!D35) | E14: ='Historical Financial Statements'!E14/(('Historical Financial Statements'!E33+'Historical Financial Statements'!E34)+'Historical Financial Statements'!E35) | F14: ='Historical Financial Statements'!F14/(('Historical Financial Statements'!F33+'Historical Financial Statements'!F34)+'Historical Financial Statements'!F35) | G14: ='Historical Financial Statements'!G14/(('Historical Financial Statements'!G33+'Historical Financial Statements'!G34)+'Historical Financial Statements'!G35) | H14: ='Forecast Financial Statements'!H14/(('Forecast Financial Statements'!H28+'Forecast Financial Statements'!H29)+'Forecast Financial Statements'!H72) | I14: ='Forecast Financial Statements'!I14/(('Forecast Financial Statements'!I28+'Forecast Financial Statements'!I29)+'Forecast Financial Statements'!I72) | J14: ='Forecast Financial Statements'!J14/(('Forecast Financial Statements'!J28+'Forecast Financial Statements'!J29)+'Forecast Financial Statements'!J72) | K14: ='Forecast Financial Statements'!K14/(('Forecast Financial Statements'!K28+'Forecast Financial Statements'!K29)+'Forecast Financial Statements'!K72) | L14: ='Forecast Financial Statements'!L14/(('Forecast Financial Statements'!L28+'Forecast Financial Statements'!L29)+'Forecast Financial Statements'!L72) | M14: ='Forecast Financial Statements'!M14/(('Forecast Financial Statements'!M28+'Forecast Financial Statements'!M29)+'Forecast Financial Statements'!M72) | N14: ='Forecast Financial Statements'!N14/(('Forecast Financial Statements'!N28+'Forecast Financial Statements'!N29)+'Forecast Financial Statements'!N72) | O14: ='Forecast Financial Statements'!O14/(('Forecast Financial Statements'!O28+'Forecast Financial Statements'!O29)+'Forecast Financial Statements'!O72)
A15: ROA % | B15: ='Historical Financial Statements'!B20/'Historical Financial Statements'!B32 | C15: ='Historical Financial Statements'!C20/'Historical Financial Statements'!C32 | D15: ='Historical Financial Statements'!D20/'Historical Financial Statements'!D32 | E15: ='Historical Financial Statements'!E20/'Historical Financial Statements'!E32 | F15: ='Historical Financial Statements'!F20/'Historical Financial Statements'!F32 | G15: ='Historical Financial Statements'!G20/'Historical Financial Statements'!G32 | H15: ='Forecast Financial Statements'!H20/'Forecast Financial Statements'!H70 | I15: ='Forecast Financial Statements'!I20/'Forecast Financial Statements'!I70 | J15: ='Forecast Financial Statements'!J20/'Forecast Financial Statements'!J70 | K15: ='Forecast Financial Statements'!K20/'Forecast Financial Statements'!K70 | L15: ='Forecast Financial Statements'!L20/'Forecast Financial Statements'!L70 | M15: ='Forecast Financial Statements'!M20/'Forecast Financial Statements'!M70 | N15: ='Forecast Financial Statements'!N20/'Forecast Financial Statements'!N70 | O15: ='Forecast Financial Statements'!O20/'Forecast Financial Statements'!O70
A16: Asset turnover (x) | B16: ='Historical Financial Statements'!B5/'Historical Financial Statements'!B32 | C16: ='Historical Financial Statements'!C5/'Historical Financial Statements'!C32 | D16: ='Historical Financial Statements'!D5/'Historical Financial Statements'!D32 | E16: ='Historical Financial Statements'!E5/'Historical Financial Statements'!E32 | F16: ='Historical Financial Statements'!F5/'Historical Financial Statements'!F32 | G16: ='Historical Financial Statements'!G5/'Historical Financial Statements'!G32 | H16: ='Forecast Financial Statements'!H5/'Forecast Financial Statements'!H70 | I16: ='Forecast Financial Statements'!I5/'Forecast Financial Statements'!I70 | J16: ='Forecast Financial Statements'!J5/'Forecast Financial Statements'!J70 | K16: ='Forecast Financial Statements'!K5/'Forecast Financial Statements'!K70 | L16: ='Forecast Financial Statements'!L5/'Forecast Financial Statements'!L70 | M16: ='Forecast Financial Statements'!M5/'Forecast Financial Statements'!M70 | N16: ='Forecast Financial Statements'!N5/'Forecast Financial Statements'!N70 | O16: ='Forecast Financial Statements'!O5/'Forecast Financial Statements'!O70
A18: Leverage & coverage
A19: Debt / equity (x) | B19: ='Historical Financial Statements'!B35/('Historical Financial Statements'!B33+'Historical Financial Statements'!B34) | C19: ='Historical Financial Statements'!C35/('Historical Financial Statements'!C33+'Historical Financial Statements'!C34) | D19: ='Historical Financial Statements'!D35/('Historical Financial Statements'!D33+'Historical Financial Statements'!D34) | E19: ='Historical Financial Statements'!E35/('Historical Financial Statements'!E33+'Historical Financial Statements'!E34) | F19: ='Historical Financial Statements'!F35/('Historical Financial Statements'!F33+'Historical Financial Statements'!F34) | G19: ='Historical Financial Statements'!G35/('Historical Financial Statements'!G33+'Historical Financial Statements'!G34) | H19: ='Forecast Financial Statements'!H72/('Forecast Financial Statements'!H28+'Forecast Financial Statements'!H29) | I19: ='Forecast Financial Statements'!I72/('Forecast Financial Statements'!I28+'Forecast Financial Statements'!I29) | J19: ='Forecast Financial Statements'!J72/('Forecast Financial Statements'!J28+'Forecast Financial Statements'!J29) | K19: ='Forecast Financial Statements'!K72/('Forecast Financial Statements'!K28+'Forecast Financial Statements'!K29) | L19: ='Forecast Financial Statements'!L72/('Forecast Financial Statements'!L28+'Forecast Financial Statements'!L29) | M19: ='Forecast Financial Statements'!M72/('Forecast Financial Statements'!M28+'Forecast Financial Statements'!M29) | N19: ='Forecast Financial Statements'!N72/('Forecast Financial Statements'!N28+'Forecast Financial Statements'!N29) | O19: ='Forecast Financial Statements'!O72/('Forecast Financial Statements'!O28+'Forecast Financial Statements'!O29)
A20: Interest coverage (x) | B20: ='Historical Financial Statements'!B14/'Historical Financial Statements'!B16 | C20: ='Historical Financial Statements'!C14/'Historical Financial Statements'!C16 | D20: ='Historical Financial Statements'!D14/'Historical Financial Statements'!D16 | E20: ='Historical Financial Statements'!E14/'Historical Financial Statements'!E16 | F20: ='Historical Financial Statements'!F14/'Historical Financial Statements'!F16 | G20: ='Historical Financial Statements'!G14/'Historical Financial Statements'!G16 | H20: ='Forecast Financial Statements'!H14/'Forecast Financial Statements'!H16 | I20: ='Forecast Financial Statements'!I14/'Forecast Financial Statements'!I16 | J20: ='Forecast Financial Statements'!J14/'Forecast Financial Statements'!J16 | K20: ='Forecast Financial Statements'!K14/'Forecast Financial Statements'!K16 | L20: ='Forecast Financial Statements'!L14/'Forecast Financial Statements'!L16 | M20: ='Forecast Financial Statements'!M14/'Forecast Financial Statements'!M16 | N20: ='Forecast Financial Statements'!N14/'Forecast Financial Statements'!N16 | O20: ='Forecast Financial Statements'!O14/'Forecast Financial Statements'!O16
A21: Net debt / EBITDA (x) | H21: =('Forecast Financial Statements'!H72-'Forecast Financial Statements'!H67)/'Forecast Financial Statements'!H12 | I21: =('Forecast Financial Statements'!I72-'Forecast Financial Statements'!I67)/'Forecast Financial Statements'!I12 | J21: =('Forecast Financial Statements'!J72-'Forecast Financial Statements'!J67)/'Forecast Financial Statements'!J12 | K21: =('Forecast Financial Statements'!K72-'Forecast Financial Statements'!K67)/'Forecast Financial Statements'!K12 | L21: =('Forecast Financial Statements'!L72-'Forecast Financial Statements'!L67)/'Forecast Financial Statements'!L12 | M21: =('Forecast Financial Statements'!M72-'Forecast Financial Statements'!M67)/'Forecast Financial Statements'!M12 | N21: =('Forecast Financial Statements'!N72-'Forecast Financial Statements'!N67)/'Forecast Financial Statements'!N12 | O21: =('Forecast Financial Statements'!O72-'Forecast Financial Statements'!O67)/'Forecast Financial Statements'!O12
A23: Per share & payout
A24: EPS (INR) | B24: ='Historical Financial Statements'!B21 | C24: ='Historical Financial Statements'!C21 | D24: ='Historical Financial Statements'!D21 | E24: ='Historical Financial Statements'!E21 | F24: ='Historical Financial Statements'!F21 | G24: ='Historical Financial Statements'!G21 | H24: ='Forecast Financial Statements'!H21 | I24: ='Forecast Financial Statements'!I21 | J24: ='Forecast Financial Statements'!J21 | K24: ='Forecast Financial Statements'!K21 | L24: ='Forecast Financial Statements'!L21 | M24: ='Forecast Financial Statements'!M21 | N24: ='Forecast Financial Statements'!N21 | O24: ='Forecast Financial Statements'!O21
A25: DPS (INR) | B25: ='Historical Financial Statements'!B22/'Assumptions'!C66 | C25: ='Historical Financial Statements'!C22/'Assumptions'!C66 | D25: ='Historical Financial Statements'!D22/'Assumptions'!C66 | E25: ='Historical Financial Statements'!E22/'Assumptions'!C66 | F25: ='Historical Financial Statements'!F22/'Assumptions'!C66 | G25: ='Historical Financial Statements'!G22/'Assumptions'!C66 | H25: ='Forecast Financial Statements'!H22/'Assumptions'!C66 | I25: ='Forecast Financial Statements'!I22/'Assumptions'!C66 | J25: ='Forecast Financial Statements'!J22/'Assumptions'!C66 | K25: ='Forecast Financial Statements'!K22/'Assumptions'!C66 | L25: ='Forecast Financial Statements'!L22/'Assumptions'!C66 | M25: ='Forecast Financial Statements'!M22/'Assumptions'!C66 | N25: ='Forecast Financial Statements'!N22/'Assumptions'!C66 | O25: ='Forecast Financial Statements'!O22/'Assumptions'!C66
A26: Dividend payout % | B26: =IF('Historical Financial Statements'!B20=0,0,'Historical Financial Statements'!B22/'Historical Financial Statements'!B20) | C26: =IF('Historical Financial Statements'!C20=0,0,'Historical Financial Statements'!C22/'Historical Financial Statements'!C20) | D26: =IF('Historical Financial Statements'!D20=0,0,'Historical Financial Statements'!D22/'Historical Financial Statements'!D20) | E26: =IF('Historical Financial Statements'!E20=0,0,'Historical Financial Statements'!E22/'Historical Financial Statements'!E20) | F26: =IF('Historical Financial Statements'!F20=0,0,'Historical Financial Statements'!F22/'Historical Financial Statements'!F20) | G26: =IF('Historical Financial Statements'!G20=0,0,'Historical Financial Statements'!G22/'Historical Financial Statements'!G20) | H26: =IF('Forecast Financial Statements'!H20=0,0,'Forecast Financial Statements'!H22/'Forecast Financial Statements'!H20) | I26: =IF('Forecast Financial Statements'!I20=0,0,'Forecast Financial Statements'!I22/'Forecast Financial Statements'!I20) | J26: =IF('Forecast Financial Statements'!J20=0,0,'Forecast Financial Statements'!J22/'Forecast Financial Statements'!J20) | K26: =IF('Forecast Financial Statements'!K20=0,0,'Forecast Financial Statements'!K22/'Forecast Financial Statements'!K20) | L26: =IF('Forecast Financial Statements'!L20=0,0,'Forecast Financial Statements'!L22/'Forecast Financial Statements'!L20) | M26: =IF('Forecast Financial Statements'!M20=0,0,'Forecast Financial Statements'!M22/'Forecast Financial Statements'!M20) | N26: =IF('Forecast Financial Statements'!N20=0,0,'Forecast Financial Statements'!N22/'Forecast Financial Statements'!N20) | O26: =IF('Forecast Financial Statements'!O20=0,0,'Forecast Financial Statements'!O22/'Forecast Financial Statements'!O20)
A27: Book value per share (INR) | B27: =('Historical Financial Statements'!B33+'Historical Financial Statements'!B34)/'Assumptions'!C66 | C27: =('Historical Financial Statements'!C33+'Historical Financial Statements'!C34)/'Assumptions'!C66 | D27: =('Historical Financial Statements'!D33+'Historical Financial Statements'!D34)/'Assumptions'!C66 | E27: =('Historical Financial Statements'!E33+'Historical Financial Statements'!E34)/'Assumptions'!C66 | F27: =('Historical Financial Statements'!F33+'Historical Financial Statements'!F34)/'Assumptions'!C66 | G27: =('Historical Financial Statements'!G33+'Historical Financial Statements'!G34)/'Assumptions'!C66 | H27: =('Forecast Financial Statements'!H28+'Forecast Financial Statements'!H29)/'Assumptions'!C66 | I27: =('Forecast Financial Statements'!I28+'Forecast Financial Statements'!I29)/'Assumptions'!C66 | J27: =('Forecast Financial Statements'!J28+'Forecast Financial Statements'!J29)/'Assumptions'!C66 | K27: =('Forecast Financial Statements'!K28+'Forecast Financial Statements'!K29)/'Assumptions'!C66 | L27: =('Forecast Financial Statements'!L28+'Forecast Financial Statements'!L29)/'Assumptions'!C66 | M27: =('Forecast Financial Statements'!M28+'Forecast Financial Statements'!M29)/'Assumptions'!C66 | N27: =('Forecast Financial Statements'!N28+'Forecast Financial Statements'!N29)/'Assumptions'!C66 | O27: =('Forecast Financial Statements'!O28+'Forecast Financial Statements'!O29)/'Assumptions'!C66
A29: Working capital & cash flow (forecast)
A30: Receivable days | H30: ='Forecast Financial Statements'!H63/'Forecast Financial Statements'!H5*365 | I30: ='Forecast Financial Statements'!I63/'Forecast Financial Statements'!I5*365 | J30: ='Forecast Financial Statements'!J63/'Forecast Financial Statements'!J5*365 | K30: ='Forecast Financial Statements'!K63/'Forecast Financial Statements'!K5*365 | L30: ='Forecast Financial Statements'!L63/'Forecast Financial Statements'!L5*365 | M30: ='Forecast Financial Statements'!M63/'Forecast Financial Statements'!M5*365 | N30: ='Forecast Financial Statements'!N63/'Forecast Financial Statements'!N5*365 | O30: ='Forecast Financial Statements'!O63/'Forecast Financial Statements'!O5*365
A31: Inventory days | I31: ='Forecast Financial Statements'!I64/'Cost Forecast'!I24*365 | J31: ='Forecast Financial Statements'!J64/'Cost Forecast'!J24*365 | K31: ='Forecast Financial Statements'!K64/'Cost Forecast'!K24*365 | L31: ='Forecast Financial Statements'!L64/'Cost Forecast'!L24*365 | M31: ='Forecast Financial Statements'!M64/'Cost Forecast'!M24*365 | N31: ='Forecast Financial Statements'!N64/'Cost Forecast'!N24*365 | O31: ='Forecast Financial Statements'!O64/'Cost Forecast'!O24*365
A32: Payable days | I32: ='Forecast Financial Statements'!I42/'Cost Forecast'!I24*365 | J32: ='Forecast Financial Statements'!J42/'Cost Forecast'!J24*365 | K32: ='Forecast Financial Statements'!K42/'Cost Forecast'!K24*365 | L32: ='Forecast Financial Statements'!L42/'Cost Forecast'!L24*365 | M32: ='Forecast Financial Statements'!M42/'Cost Forecast'!M24*365 | N32: ='Forecast Financial Statements'!N42/'Cost Forecast'!N24*365 | O32: ='Forecast Financial Statements'!O42/'Cost Forecast'!O24*365
A33: FCFF (INR Cr) | I33: ='DCF Valuation'!I12 | J33: ='DCF Valuation'!J12 | K33: ='DCF Valuation'!K12 | L33: ='DCF Valuation'!L12 | M33: ='DCF Valuation'!M12 | N33: ='DCF Valuation'!N12 | O33: ='DCF Valuation'!O12
A34: Capex / sales % | I34: ='Assumptions'!I35/'Forecast Financial Statements'!I5 | J34: ='Assumptions'!J35/'Forecast Financial Statements'!J5 | K34: ='Assumptions'!K35/'Forecast Financial Statements'!K5 | L34: ='Assumptions'!L35/'Forecast Financial Statements'!L5 | M34: ='Assumptions'!M35/'Forecast Financial Statements'!M5 | N34: ='Assumptions'!N35/'Forecast Financial Statements'!N5 | O34: ='Assumptions'!O35/'Forecast Financial Statements'!O5
A35: FCFE (INR Cr) | I35: ='DCF Valuation'!I12-'Forecast Financial Statements'!I16*(1-'Assumptions'!I46)+'Debt Schedule'!I7+'Debt Schedule'!I8 | J35: ='DCF Valuation'!J12-'Forecast Financial Statements'!J16*(1-'Assumptions'!J46)+'Debt Schedule'!J7+'Debt Schedule'!J8 | K35: ='DCF Valuation'!K12-'Forecast Financial Statements'!K16*(1-'Assumptions'!K46)+'Debt Schedule'!K7+'Debt Schedule'!K8 | L35: ='DCF Valuation'!L12-'Forecast Financial Statements'!L16*(1-'Assumptions'!L46)+'Debt Schedule'!L7+'Debt Schedule'!L8 | M35: ='DCF Valuation'!M12-'Forecast Financial Statements'!M16*(1-'Assumptions'!M46)+'Debt Schedule'!M7+'Debt Schedule'!M8 | N35: ='DCF Valuation'!N12-'Forecast Financial Statements'!N16*(1-'Assumptions'!N46)+'Debt Schedule'!N7+'Debt Schedule'!N8 | O35: ='DCF Valuation'!O12-'Forecast Financial Statements'!O16*(1-'Assumptions'!O46)+'Debt Schedule'!O7+'Debt Schedule'!O8

Sheet DCF Valuation
A1: DCF VALUATION
A2: Free Cash Flow to Firm (FCFF) valuation; WACC computed dynamically on Assumptions.
A4: INR Crore | I4: FY2027 | J4: FY2028 | K4: FY2029 | L4: FY2030 | M4: FY2031 | N4: FY2032 | O4: FY2033
A5: A. Unlevered free cash flow
A6: EBIT | I6: ='Forecast Financial Statements'!I14 | J6: ='Forecast Financial Statements'!J14 | K6: ='Forecast Financial Statements'!K14 | L6: ='Forecast Financial Statements'!L14 | M6: ='Forecast Financial Statements'!M14 | N6: ='Forecast Financial Statements'!N14 | O6: ='Forecast Financial Statements'!O14
A7: Less: cash taxes on EBIT | I7: =-I6*'Assumptions'!I46 | J7: =-J6*'Assumptions'!J46 | K7: =-K6*'Assumptions'!K46 | L7: =-L6*'Assumptions'!L46 | M7: =-M6*'Assumptions'!M46 | N7: =-N6*'Assumptions'!N46 | O7: =-O6*'Assumptions'!O46
A8: NOPAT | I8: =I6+I7 | J8: =J6+J7 | K8: =K6+K7 | L8: =L6+L7 | M8: =M6+M7 | N8: =N6+N7 | O8: =O6+O7
A9: Add: depreciation & amortisation | I9: ='Depreciation Schedule'!I8 | J9: ='Depreciation Schedule'!J8 | K9: ='Depreciation Schedule'!K8 | L9: ='Depreciation Schedule'!L8 | M9: ='Depreciation Schedule'!M8 | N9: ='Depreciation Schedule'!N8 | O9: ='Depreciation Schedule'!O8
A10: Less: capital expenditure | I10: =-'Assumptions'!I35 | J10: =-'Assumptions'!J35 | K10: =-'Assumptions'!K35 | L10: =-'Assumptions'!L35 | M10: =-'Assumptions'!M35 | N10: =-'Assumptions'!N35 | O10: =-'Assumptions'!O35
A11: Add/(less): change in working capital | I11: ='Working Capital Schedule'!I18 | J11: ='Working Capital Schedule'!J18 | K11: ='Working Capital Schedule'!K18 | L11: ='Working Capital Schedule'!L18 | M11: ='Working Capital Schedule'!M18 | N11: ='Working Capital Schedule'!N18 | O11: ='Working Capital Schedule'!O18
A12: Free cash flow to firm (FCFF) | I12: =I8+I9+I10+I11 | J12: =J8+J9+J10+J11 | K12: =K8+K9+K10+K11 | L12: =L8+L9+L10+L11 | M12: =M8+M9+M10+M11 | N12: =N8+N9+N10+N11 | O12: =O8+O9+O10+O11
A13: Discount period (years) | I13: 1 | J13: 2 | K13: 3 | L13: 4 | M13: 5 | N13: 6 | O13: 7
A14: Discount factor @ WACC | I14: =1/(1+'Assumptions'!C65)^I13 | J14: =1/(1+'Assumptions'!C65)^J13 | K14: =1/(1+'Assumptions'!C65)^K13 | L14: =1/(1+'Assumptions'!C65)^L13 | M14: =1/(1+'Assumptions'!C65)^M13 | N14: =1/(1+'Assumptions'!C65)^N13 | O14: =1/(1+'Assumptions'!C65)^O13
A15: PV of FCFF | I15: =I12*I14 | J15: =J12*J14 | K15: =K12*K14 | L15: =L12*L14 | M15: =M12*M14 | N15: =N12*N14 | O15: =O12*O14
A17: B. Enterprise & equity value
A18: Sum of PV of explicit FCFF (FY27-33) | C18: =SUM(I15:O15)
A19: WACC | C19: ='Assumptions'!C65
A20: Terminal growth rate (g) | C20: ='Assumptions'!C63
A21: Terminal value (Gordon growth) | C21: =O12*(1+C20)/(C19-C20)
A22: PV of terminal value | C22: =C21*O14
A23: Enterprise value (EV) | C23: =C18+C22
A24: Less: net debt (FY26 debt - cash) | C24: =-('Forecast Financial Statements'!H72-'Forecast Financial Statements'!H67)
A25: Equity value | C25: =C23+C24
A26: Shares outstanding (crore) | C26: ='Assumptions'!C66
A27: Intrinsic value per share (INR) | C27: =C25/C26
A28: Current market price (INR) | C28: ='Assumptions'!C67
A29: Upside / (downside) | C29: =C27/C28-1

Sheet Relative Valuation
A1: RELATIVE VALUATION
A2: Peer trading multiples are INDICATIVE; refresh with live market data before use.
A4: A. Peer trading multiples (indicative)
A5: Peer company | B5: EV/Revenue (x) | C5: EV/EBITDA (x) | D5: P/E (x) | E5: P/B (x) | F5: Div yield %
A6: Siemens India | B6: 5.5 | C6: 42 | D6: 60 | E6: 9 | F6: 0.4
A7: ABB India | B7: 7 | C7: 50 | D7: 68 | E7: 14 | F7: 0.4
A8: CG Power & Ind. | B8: 6.5 | C8: 45 | D8: 62 | E8: 18 | F8: 0.2
A9: GE Vernova T&D India | B9: 8 | C9: 48 | D9: 65 | E9: 20 | F9: 0.1
A10: Thermax | B10: 4 | C10: 38 | D10: 55 | E10: 8 | F10: 0.3
A11: Triveni Turbine | B11: 7.5 | C11: 40 | D11: 52 | E11: 16 | F11: 0.5
A12: Larsen & Toubro | B12: 2 | C12: 22 | D12: 32 | E12: 5 | F12: 0.7
A13: Kalpataru Projects | B13: 0.9 | C13: 12 | D13: 22 | E13: 3 | F13: 0.4
A14: Median | B14: =MEDIAN(B6:B13) | C14: =MEDIAN(C6:C13) | D14: =MEDIAN(D6:D13) | E14: =MEDIAN(E6:E13) | F14: =MEDIAN(F6:F13)
A16: B. Implied valuation for BHEL (on FY2027E)
A17: BHEL FY2027E revenue | C17: ='Forecast Financial Statements'!I5
A18: BHEL FY2027E EBITDA | C18: ='Forecast Financial Statements'!I12
A19: BHEL FY2027E EPS (INR) | C19: ='Forecast Financial Statements'!I21
A20: Net debt (FY26) | C20: ='Forecast Financial Statements'!H72-'Forecast Financial Statements'!H67
A22: Implied EV (EV/EBITDA method) | C22: =C18*C14
A23: Implied equity value (EV/EBITDA) | C23: =C22-C20
A24: Implied price - EV/EBITDA (INR) | C24: =C23/'Assumptions'!C66
A25: Implied price - P/E method (INR) | C25: =C19*D14
A26: Implied EV (EV/Revenue method) | C26: =C17*B14
A27: Implied price - EV/Revenue (INR) | C27: =(C26-C20)/'Assumptions'!C66
A29: Average implied target price (INR) | C29: =AVERAGE(C24,C25,C27)

Sheet Sensitivity Analysis
A1: SENSITIVITY ANALYSIS
A2: Two-way table: intrinsic value per share (INR) vs WACC and terminal growth. Centre = base case.
B4: Intrinsic value/share (INR)
B5: WACC \ g | C5: ='Assumptions'!C63+-0.015 | D5: ='Assumptions'!C63+-0.0075 | E5: ='Assumptions'!C63+0.0 | F5: ='Assumptions'!C63+0.0075 | G5: ='Assumptions'!C63+0.015
B6: ='Assumptions'!C65+0.02 | C6: =(SUMPRODUCT('DCF Valuation'!$I$12:$O$12,(1+$B6)^(-'DCF Valuation'!$I$13:$O$13))+('DCF Valuation'!$O$12*(1+C$5)/($B6-C$5))*(1+$B6)^(-7)+'DCF Valuation'!$C$24)/'DCF Valuation'!$C$26 | D6: =(SUMPRODUCT('DCF Valuation'!$I$12:$O$12,(1+$B6)^(-'DCF Valuation'!$I$13:$O$13))+('DCF Valuation'!$O$12*(1+D$5)/($B6-D$5))*(1+$B6)^(-7)+'DCF Valuation'!$C$24)/'DCF Valuation'!$C$26 | E6: =(SUMPRODUCT('DCF Valuation'!$I$12:$O$12,(1+$B6)^(-'DCF Valuation'!$I$13:$O$13))+('DCF Valuation'!$O$12*(1+E$5)/($B6-E$5))*(1+$B6)^(-7)+'DCF Valuation'!$C$24)/'DCF Valuation'!$C$26 | F6: =(SUMPRODUCT('DCF Valuation'!$I$12:$O$12,(1+$B6)^(-'DCF Valuation'!$I$13:$O$13))+('DCF Valuation'!$O$12*(1+F$5)/($B6-F$5))*(1+$B6)^(-7)+'DCF Valuation'!$C$24)/'DCF Valuation'!$C$26 | G6: =(SUMPRODUCT('DCF Valuation'!$I$12:$O$12,(1+$B6)^(-'DCF Valuation'!$I$13:$O$13))+('DCF Valuation'!$O$12*(1+G$5)/($B6-G$5))*(1+$B6)^(-7)+'DCF Valuation'!$C$24)/'DCF Valuation'!$C$26
B7: ='Assumptions'!C65+0.01 | C7: =(SUMPRODUCT('DCF Valuation'!$I$12:$O$12,(1+$B7)^(-'DCF Valuation'!$I$13:$O$13))+('DCF Valuation'!$O$12*(1+C$5)/($B7-C$5))*(1+$B7)^(-7)+'DCF Valuation'!$C$24)/'DCF Valuation'!$C$26 | D7: =(SUMPRODUCT('DCF Valuation'!$I$12:$O$12,(1+$B7)^(-'DCF Valuation'!$I$13:$O$13))+('DCF Valuation'!$O$12*(1+D$5)/($B7-D$5))*(1+$B7)^(-7)+'DCF Valuation'!$C$24)/'DCF Valuation'!$C$26 | E7: =(SUMPRODUCT('DCF Valuation'!$I$12:$O$12,(1+$B7)^(-'DCF Valuation'!$I$13:$O$13))+('DCF Valuation'!$O$12*(1+E$5)/($B7-E$5))*(1+$B7)^(-7)+'DCF Valuation'!$C$24)/'DCF Valuation'!$C$26 | F7: =(SUMPRODUCT('DCF Valuation'!$I$12:$O$12,(1+$B7)^(-'DCF Valuation'!$I$13:$O$13))+('DCF Valuation'!$O$12*(1+F$5)/($B7-F$5))*(1+$B7)^(-7)+'DCF Valuation'!$C$24)/'DCF Valuation'!$C$26 | G7: =(SUMPRODUCT('DCF Valuation'!$I$12:$O$12,(1+$B7)^(-'DCF Valuation'!$I$13:$O$13))+('DCF Valuation'!$O$12*(1+G$5)/($B7-G$5))*(1+$B7)^(-7)+'DCF Valuation'!$C$24)/'DCF Valuation'!$C$26
B8: ='Assumptions'!C65+0.0 | C8: =(SUMPRODUCT('DCF Valuation'!$I$12:$O$12,(1+$B8)^(-'DCF Valuation'!$I$13:$O$13))+('DCF Valuation'!$O$12*(1+C$5)/($B8-C$5))*(1+$B8)^(-7)+'DCF Valuation'!$C$24)/'DCF Valuation'!$C$26 | D8: =(SUMPRODUCT('DCF Valuation'!$I$12:$O$12,(1+$B8)^(-'DCF Valuation'!$I$13:$O$13))+('DCF Valuation'!$O$12*(1+D$5)/($B8-D$5))*(1+$B8)^(-7)+'DCF Valuation'!$C$24)/'DCF Valuation'!$C$26 | E8: =(SUMPRODUCT('DCF Valuation'!$I$12:$O$12,(1+$B8)^(-'DCF Valuation'!$I$13:$O$13))+('DCF Valuation'!$O$12*(1+E$5)/($B8-E$5))*(1+$B8)^(-7)+'DCF Valuation'!$C$24)/'DCF Valuation'!$C$26 | F8: =(SUMPRODUCT('DCF Valuation'!$I$12:$O$12,(1+$B8)^(-'DCF Valuation'!$I$13:$O$13))+('DCF Valuation'!$O$12*(1+F$5)/($B8-F$5))*(1+$B8)^(-7)+'DCF Valuation'!$C$24)/'DCF Valuation'!$C$26 | G8: =(SUMPRODUCT('DCF Valuation'!$I$12:$O$12,(1+$B8)^(-'DCF Valuation'!$I$13:$O$13))+('DCF Valuation'!$O$12*(1+G$5)/($B8-G$5))*(1+$B8)^(-7)+'DCF Valuation'!$C$24)/'DCF Valuation'!$C$26
B9: ='Assumptions'!C65+-0.01 | C9: =(SUMPRODUCT('DCF Valuation'!$I$12:$O$12,(1+$B9)^(-'DCF Valuation'!$I$13:$O$13))+('DCF Valuation'!$O$12*(1+C$5)/($B9-C$5))*(1+$B9)^(-7)+'DCF Valuation'!$C$24)/'DCF Valuation'!$C$26 | D9: =(SUMPRODUCT('DCF Valuation'!$I$12:$O$12,(1+$B9)^(-'DCF Valuation'!$I$13:$O$13))+('DCF Valuation'!$O$12*(1+D$5)/($B9-D$5))*(1+$B9)^(-7)+'DCF Valuation'!$C$24)/'DCF Valuation'!$C$26 | E9: =(SUMPRODUCT('DCF Valuation'!$I$12:$O$12,(1+$B9)^(-'DCF Valuation'!$I$13:$O$13))+('DCF Valuation'!$O$12*(1+E$5)/($B9-E$5))*(1+$B9)^(-7)+'DCF Valuation'!$C$24)/'DCF Valuation'!$C$26 | F9: =(SUMPRODUCT('DCF Valuation'!$I$12:$O$12,(1+$B9)^(-'DCF Valuation'!$I$13:$O$13))+('DCF Valuation'!$O$12*(1+F$5)/($B9-F$5))*(1+$B9)^(-7)+'DCF Valuation'!$C$24)/'DCF Valuation'!$C$26 | G9: =(SUMPRODUCT('DCF Valuation'!$I$12:$O$12,(1+$B9)^(-'DCF Valuation'!$I$13:$O$13))+('DCF Valuation'!$O$12*(1+G$5)/($B9-G$5))*(1+$B9)^(-7)+'DCF Valuation'!$C$24)/'DCF Valuation'!$C$26
B10: ='Assumptions'!C65+-0.02 | C10: =(SUMPRODUCT('DCF Valuation'!$I$12:$O$12,(1+$B10)^(-'DCF Valuation'!$I$13:$O$13))+('DCF Valuation'!$O$12*(1+C$5)/($B10-C$5))*(1+$B10)^(-7)+'DCF Valuation'!$C$24)/'DCF Valuation'!$C$26 | D10: =(SUMPRODUCT('DCF Valuation'!$I$12:$O$12,(1+$B10)^(-'DCF Valuation'!$I$13:$O$13))+('DCF Valuation'!$O$12*(1+D$5)/($B10-D$5))*(1+$B10)^(-7)+'DCF Valuation'!$C$24)/'DCF Valuation'!$C$26 | E10: =(SUMPRODUCT('DCF Valuation'!$I$12:$O$12,(1+$B10)^(-'DCF Valuation'!$I$13:$O$13))+('DCF Valuation'!$O$12*(1+E$5)/($B10-E$5))*(1+$B10)^(-7)+'DCF Valuation'!$C$24)/'DCF Valuation'!$C$26 | F10: =(SUMPRODUCT('DCF Valuation'!$I$12:$O$12,(1+$B10)^(-'DCF Valuation'!$I$13:$O$13))+('DCF Valuation'!$O$12*(1+F$5)/($B10-F$5))*(1+$B10)^(-7)+'DCF Valuation'!$C$24)/'DCF Valuation'!$C$26 | G10: =(SUMPRODUCT('DCF Valuation'!$I$12:$O$12,(1+$B10)^(-'DCF Valuation'!$I$13:$O$13))+('DCF Valuation'!$O$12*(1+G$5)/($B10-G$5))*(1+$B10)^(-7)+'DCF Valuation'!$C$24)/'DCF Valuation'!$C$26
A12: Other sensitivities (order inflow, execution, margins, commodities, capex, rates, WC) are on Scenario Analysis and the Assumptions sheet.

Sheet Scenario Analysis
A1: SCENARIO ANALYSIS
A2: Bull/Base/Bear via exit EV/EBITDA on FY2033E, discounted to present. Base links to the live model.
A3: Scenario drivers & valuation
A4: Driver / output | B4: Bear case | C4: Base case | D4: Bull case
A5: FY2033E revenue (INR Cr) | B5: 68000 | C5: ='Forecast Financial Statements'!O5 | D5: 92000
A6: Terminal EBITDA margin | B6: 0.09 | C6: ='Forecast Financial Statements'!O12/'Forecast Financial Statements'!O5 | D6: 0.15
A7: Exit EV/EBITDA multiple (x) | B7: 14 | C7: 18 | D7: 24
A8: WACC | B8: 0.155 | C8: ='Assumptions'!C65 | D8: 0.12
A9: FY2033E EBITDA (INR Cr) | B9: =B5*B6 | C9: =C5*C6 | D9: =D5*D6
A10: Terminal EV (INR Cr) | B10: =B9*B7 | C10: =C9*C7 | D10: =D9*D7
A11: PV of EV (discounted 7y) | B11: =B10/(1+B8)^7 | C11: =C10/(1+C8)^7 | D11: =D10/(1+D8)^7
A12: Less: net debt (FY26) | B12: ='Forecast Financial Statements'!H72-'Forecast Financial Statements'!H67 | C12: ='Forecast Financial Statements'!H72-'Forecast Financial Statements'!H67 | D12: ='Forecast Financial Statements'!H72-'Forecast Financial Statements'!H67
A13: Equity value (INR Cr) | B13: =B11-B12 | C13: =C11-C12 | D13: =D11-D12
A14: Target price (INR) | B14: =B13/'Assumptions'!C66 | C14: =C13/'Assumptions'!C66 | D14: =D13/'Assumptions'!C66
A15: Scenario probability | B15: 0.25 | C15: 0.5 | D15: 0.25
A17: Probability-weighted target price (INR) | B17: =SUMPRODUCT(B14:D14,B15:D15)

Sheet Dashboard
A1: BHEL | EXECUTIVE DASHBOARD
A3: DCF value / share (INR) | B3: Current price (INR) | D3: Upside / (downside) | E3: Prob-weighted TP (INR) | G3: Avg relative TP (INR) | H3: WACC
A4: ='DCF Valuation'!C27 | B4: ='DCF Valuation'!C28 | D4: ='DCF Valuation'!C29 | E4: ='Scenario Analysis'!B17 | G4: ='Relative Valuation'!C29 | H4: ='Assumptions'!C65
A6: FY27E revenue (INR Cr) | B6: FY33E revenue (INR Cr) | D6: FY27E EBITDA margin | E6: FY33E EBITDA margin | G6: FY26 order book (INR Cr) | H6: FY33E PAT (INR Cr)
A7: ='Forecast Financial Statements'!I5 | B7: ='Forecast Financial Statements'!O5 | D7: ='Forecast Financial Statements'!I12/'Forecast Financial Statements'!I5 | E7: ='Forecast Financial Statements'!O12/'Forecast Financial Statements'!O5 | G7: ='Revenue Build-up'!H10 | H7: ='Forecast Financial Statements'!O20
A9: DCF bridge (INR Cr)
A10: PV of explicit FCFF | B10: ='DCF Valuation'!C18
A11: PV of terminal value | B11: ='DCF Valuation'!C22
A12: Enterprise value | B12: ='DCF Valuation'!C23
A13: Less: net debt | B13: ='DCF Valuation'!C24
A14: Equity value | B14: ='DCF Valuation'!C25

Sheet Error Checks
A1: ERROR CHECKS
A2: Automated integrity checks. "OK" = pass (difference < INR 0.5 Cr).
A4: Check | H4: FY2026 | I4: FY2027 | J4: FY2028 | K4: FY2029 | L4: FY2030 | M4: FY2031 | N4: FY2032 | O4: FY2033
A5: Balance sheet balances (TA = TE&L) | B5: =IF(ABS('Forecast Financial Statements'!B70-'Forecast Financial Statements'!B49)<0.5,"OK","REVIEW") | C5: =IF(ABS('Forecast Financial Statements'!C70-'Forecast Financial Statements'!C49)<0.5,"OK","REVIEW") | D5: =IF(ABS('Forecast Financial Statements'!D70-'Forecast Financial Statements'!D49)<0.5,"OK","REVIEW") | E5: =IF(ABS('Forecast Financial Statements'!E70-'Forecast Financial Statements'!E49)<0.5,"OK","REVIEW") | F5: =IF(ABS('Forecast Financial Statements'!F70-'Forecast Financial Statements'!F49)<0.5,"OK","REVIEW") | G5: =IF(ABS('Forecast Financial Statements'!G70-'Forecast Financial Statements'!G49)<0.5,"OK","REVIEW") | H5: =IF(ABS('Forecast Financial Statements'!H70-'Forecast Financial Statements'!H49)<0.5,"OK","REVIEW") | I5: =IF(ABS('Forecast Financial Statements'!I70-'Forecast Financial Statements'!I49)<0.5,"OK","REVIEW") | ... O5: =IF(ABS('Forecast Financial Statements'!O70-'Forecast Financial Statements'!O49)<0.5,"OK","REVIEW")
A6: Cash: Balance sheet = Cash flow stmt | I6: =IF(ABS('Forecast Financial Statements'!I67-'Cash Flow Statement'!I25)<0.5,"OK","REVIEW") | J6: =IF(ABS('Forecast Financial Statements'!J67-'Cash Flow Statement'!J25)<0.5,"OK","REVIEW") | K6: =IF(ABS('Forecast Financial Statements'!K67-'Cash Flow Statement'!K25)<0.5,"OK","REVIEW") | L6: =IF(ABS('Forecast Financial Statements'!L67-'Cash Flow Statement'!L25)<0.5,"OK","REVIEW") | M6: =IF(ABS('Forecast Financial Statements'!M67-'Cash Flow Statement'!M25)<0.5,"OK","REVIEW") | N6: =IF(ABS('Forecast Financial Statements'!N67-'Cash Flow Statement'!N25)<0.5,"OK","REVIEW") | O6: =IF(ABS('Forecast Financial Statements'!O67-'Cash Flow Statement'!O25)<0.5,"OK","REVIEW")
A7: Retained earnings roll-forward ties | I7: =IF(ABS('Forecast Financial Statements'!I29-'Equity Schedule'!I10)<0.5,"OK","REVIEW") | J7: =IF(ABS('Forecast Financial Statements'!J29-'Equity Schedule'!J10)<0.5,"OK","REVIEW") | K7: =IF(ABS('Forecast Financial Statements'!K29-'Equity Schedule'!K10)<0.5,"OK","REVIEW") | L7: =IF(ABS('Forecast Financial Statements'!L29-'Equity Schedule'!L10)<0.5,"OK","REVIEW") | M7: =IF(ABS('Forecast Financial Statements'!M29-'Equity Schedule'!M10)<0.5,"OK","REVIEW") | N7: =IF(ABS('Forecast Financial Statements'!N29-'Equity Schedule'!N10)<0.5,"OK","REVIEW") | O7: =IF(ABS('Forecast Financial Statements'!O29-'Equity Schedule'!O10)<0.5,"OK","REVIEW")
A8: Debt roll-forward ties | I8: =IF(ABS('Forecast Financial Statements'!I72-'Debt Schedule'!I9)<0.5,"OK","REVIEW") | J8: =IF(ABS('Forecast Financial Statements'!J72-'Debt Schedule'!J9)<0.5,"OK","REVIEW") | K8: =IF(ABS('Forecast Financial Statements'!K72-'Debt Schedule'!K9)<0.5,"OK","REVIEW") | L8: =IF(ABS('Forecast Financial Statements'!L72-'Debt Schedule'!L9)<0.5,"OK","REVIEW") | M8: =IF(ABS('Forecast Financial Statements'!M72-'Debt Schedule'!M9)<0.5,"OK","REVIEW") | N8: =IF(ABS('Forecast Financial Statements'!N72-'Debt Schedule'!N9)<0.5,"OK","REVIEW") | O8: =IF(ABS('Forecast Financial Statements'!O72-'Debt Schedule'!O9)<0.5,"OK","REVIEW")
A9: Depreciation ties to P&L | I9: =IF(ABS('Forecast Financial Statements'!I13-'Depreciation Schedule'!I8)<0.5,"OK","REVIEW") | J9: =IF(ABS('Forecast Financial Statements'!J13-'Depreciation Schedule'!J8)<0.5,"OK","REVIEW") | K9: =IF(ABS('Forecast Financial Statements'!K13-'Depreciation Schedule'!K8)<0.5,"OK","REVIEW") | L9: =IF(ABS('Forecast Financial Statements'!L13-'Depreciation Schedule'!L8)<0.5,"OK","REVIEW") | M9: =IF(ABS('Forecast Financial Statements'!M13-'Depreciation Schedule'!M8)<0.5,"OK","REVIEW") | N9: =IF(ABS('Forecast Financial Statements'!N13-'Depreciation Schedule'!N8)<0.5,"OK","REVIEW") | O9: =IF(ABS('Forecast Financial Statements'!O13-'Depreciation Schedule'!O8)<0.5,"OK","REVIEW")
A10: Revenue ties to Revenue Build-up | I10: =IF(ABS('Forecast Financial Statements'!I5-'Revenue Build-up'!I15)<0.5,"OK","REVIEW") | J10: =IF(ABS('Forecast Financial Statements'!J5-'Revenue Build-up'!J15)<0.5,"OK","REVIEW") | K10: =IF(ABS('Forecast Financial Statements'!K5-'Revenue Build-up'!K15)<0.5,"OK","REVIEW") | L10: =IF(ABS('Forecast Financial Statements'!L5-'Revenue Build-up'!L15)<0.5,"OK","REVIEW") | M10: =IF(ABS('Forecast Financial Statements'!M5-'Revenue Build-up'!M15)<0.5,"OK","REVIEW") | N10: =IF(ABS('Forecast Financial Statements'!N5-'Revenue Build-up'!N15)<0.5,"OK","REVIEW") | O10: =IF(ABS('Forecast Financial Statements'!O5-'Revenue Build-up'!O15)<0.5,"OK","REVIEW")
A11: Net fixed assets tie to FA schedule | I11: =IF(ABS('Forecast Financial Statements'!I53-'Fixed Asset Schedule'!I10)<0.5,"OK","REVIEW") | J11: =IF(ABS('Forecast Financial Statements'!J53-'Fixed Asset Schedule'!J10)<0.5,"OK","REVIEW") | K11: =IF(ABS('Forecast Financial Statements'!K53-'Fixed Asset Schedule'!K10)<0.5,"OK","REVIEW") | L11: =IF(ABS('Forecast Financial Statements'!L53-'Fixed Asset Schedule'!L10)<0.5,"OK","REVIEW") | M11: =IF(ABS('Forecast Financial Statements'!M53-'Fixed Asset Schedule'!M10)<0.5,"OK","REVIEW") | N11: =IF(ABS('Forecast Financial Statements'!N53-'Fixed Asset Schedule'!N10)<0.5,"OK","REVIEW") | O11: =IF(ABS('Forecast Financial Statements'!O53-'Fixed Asset Schedule'!O10)<0.5,"OK","REVIEW")
A13: Historical balance check max |diff| (FY20-26) | C13: =MAX(ABS('Historical Financial Statements'!B38),ABS('Historical Financial Statements'!C38),ABS('Historical Financial Statements'!D38),ABS('Historical Financial Statements'!E38),ABS('Historical Financial Statements'!F38),ABS('Historical Financial Statements'!G38),ABS('Historical Financial Statements'!H38))
A14: Forecast balance check max |diff| | C14: =MAX(ABS('Forecast Financial Statements'!I71),ABS('Forecast Financial Statements'!J71),ABS('Forecast Financial Statements'!K71),ABS('Forecast Financial Statements'!L71),ABS('Forecast Financial Statements'!M71),ABS('Forecast Financial Statements'!N71),ABS('Forecast Financial Statements'!O71))
A15: Circular references | C15: None (interest on opening debt)
A16: Overall model status | C16: =IF(COUNTIF(B5:O11,"REVIEW")=0,"ALL CHECKS PASS","REVIEW REQUIRED")
